[{"album": {"album_type": "album", "artists": [{"external_urls": {"spotify": "https://open.spotify.com/artist/0LyfQWJT6nXafLPZqxe9Of"}, "href": "https://api.spotify.com/v1/artists/0LyfQWJT6nXafLPZqxe9Of", "id": "0LyfQWJT6nXafLPZqxe9Of", "name": "Various Artists", "type": "artist", "uri": "spotify:artist:0LyfQWJT6nXafLPZqxe9Of"}], "external_urls": {"spotify": "https://open.spotify.com/album/0BZGDrWZTc5Lc9hECNMVAl"}, "href": "https://api.spotify.com/v1/albums/0BZGDrWZTc5Lc9hECNMVAl", "id": "0BZGDrWZTc5Lc9hECNMVAl", "images": [{"height": 640, "url": "https://i.scdn.co/image/ab67616d0000b27346684ebb8f2e5ab65747b884", "width": 640}, {"height": 300, "url": "https://i.scdn.co/image/ab67616d00001e0246684ebb8f2e5ab65747b884", "width": 300}, {"height": 64, "url": "https://i.scdn.co/image/ab67616d0000485146684ebb8f2e5ab65747b884", "width": 64}], "name": "Reggaeton De Impacto Vol. 2", "release_date": "2022-02-28", "release_date_precision": "day", "total_tracks": 24, "type": "album", "uri": "spotify:album:0BZGDrWZTc5Lc9hECNMVAl"}, "artists": [{"external_urls": {"spotify": "https://open.spotify.com/artist/1wZtkThiXbVNtj6hee6dz9"}, "href": "https://api.spotify.com/v1/artists/1wZtkThiXbVNtj6hee6dz9", "id": "1wZtkThiXbVNtj6hee6dz9", "name": "Wisin & Yandel", "type": "artist", "uri": "spotify:artist:1wZtkThiXbVNtj6hee6dz9"}], "disc_number": 1, "duration_ms": 271720, "explicit": false, "external_ids": {"isrc": "USUM71018815"}, "external_urls": {"spotify": "https://open.spotify.com/track/6hpryQE1ybH9YEWiK3pKHm"}, "href": "https://api.spotify.com/v1/tracks/6hpryQE1ybH9YEWiK3pKHm", "id": "6hpryQE1ybH9YEWiK3pKHm", "is_local": false, "is_playable": true, "name": "Estoy Enamorado", "popularity": 0, "preview_url": null, "track_number": 22, "type": "track", "uri": "spotify:track:6hpryQE1ybH9YEWiK3pKHm"}, {"album": {"album_type": "album", "artists": [{"external_urls": {"spotify": "https://open.spotify.com/artist/0LyfQWJT6nXafLPZqxe9Of"}, "href": "https://api.spotify.com/v1/artists/0LyfQWJT6nXafLPZqxe9Of", "id": "0LyfQWJT6nXafLPZqxe9Of", "name": "Various Artists", "type": "artist", "uri": "spotify:artist:0LyfQWJT6nXafLPZqxe9Of"}], "external_urls": {"spotify": "https://open.spotify.com/album/2TxO1NzFUp5Z9dLa67QT0J"}, "href": "https://api.spotify.com/v1/albums/2TxO1NzFUp5Z9dLa67QT0J", "id": "2TxO1NzFUp5Z9dLa67QT0J", "images": [{"height": 640, "url": "https://i.scdn.co/image/ab67616d0000b27303446ffe27fd70ecb80f0c71", "width": 640}, {"height": 300, "url": "https://i.scdn.co/image/ab67616d00001e0203446ffe27fd70ecb80f0c71", "width": 300}, {"height": 64, "url": "https://i.scdn.co/image/ab67616d0000485103446ffe27fd70ecb80f0c71", "width": 64}], "name": "Ambiente Fiestero", "release_date": "2022-02-24", "release_date_precision": "day", "total_tracks": 40, "type": "album", "uri": "spotify:album:2TxO1NzFUp5Z9dLa67QT0J"}, "artists": [{"external_urls": {"spotify": "https://open.spotify.com/artist/1wZtkThiXbVNtj6hee6dz9"}, "href": "https://api.spotify.com/v1/artists/1wZtkThiXbVNtj6hee6dz9", "id": "1wZtkThiXbVNtj6hee6dz9", "name": "Wisin & Yandel", "type": "artist", "uri": "spotify:artist:1wZtkThiXbVNtj6hee6dz9"}], "disc_number": 1, "duration_ms": 243386, "explicit": false, "external_ids": {"isrc": "USUM71206368"}, "external_urls": {"spotify": "https://open.spotify.com/track/6TmYBIWNFywPA1xyNb7Fwg"}, "href": "https://api.spotify.com/v1/tracks/6TmYBIWNFywPA1xyNb7Fwg", "id": "6TmYBIWNFywPA1xyNb7Fwg", "is_local": false, "is_playable": true, "name": "Hipnot\u00edzame", "popularity": 0, "preview_url": null, "track_number": 35, "type": "track", "uri": "spotify:track:6TmYBIWNFywPA1xyNb7Fwg"}, {"album": {"album_type": "album", "artists": [{"external_urls": {"spotify": "https://open.spotify.com/artist/0LyfQWJT6nXafLPZqxe9Of"}, "href": "https://api.spotify.com/v1/artists/0LyfQWJT6nXafLPZqxe9Of", "id": "0LyfQWJT6nXafLPZqxe9Of", "name": "Various Artists", "type": "artist", "uri": "spotify:artist:0LyfQWJT6nXafLPZqxe9Of"}], "external_urls": {"spotify": "https://open.spotify.com/album/2zOvgcGdY0NO2qwIDaqIl6"}, "href": "https://api.spotify.com/v1/albums/2zOvgcGdY0NO2qwIDaqIl6", "id": "2zOvgcGdY0NO2qwIDaqIl6", "images": [{"height": 640, "url": "https://i.scdn.co/image/ab67616d0000b273f483b01e2e0779f2eaa008e3", "width": 640}, {"height": 300, "url": "https://i.scdn.co/image/ab67616d00001e02f483b01e2e0779f2eaa008e3", "width": 300}, {"height": 64, "url": "https://i.scdn.co/image/ab67616d00004851f483b01e2e0779f2eaa008e3", "width": 64}], "name": "Party Suprema", "release_date": "2022-02-25", "release_date_precision": "day", "total_tracks": 40, "type": "album", "uri": "spotify:album:2zOvgcGdY0NO2qwIDaqIl6"}, "artists": [{"external_urls": {"spotify": "https://open.spotify.com/artist/1wZtkThiXbVNtj6hee6dz9"}, "href": "https://api.spotify.com/v1/artists/1wZtkThiXbVNtj6hee6dz9", "id": "1wZtkThiXbVNtj6hee6dz9", "name": "Wisin & Yandel", "type": "artist", "uri": "spotify:artist:1wZtkThiXbVNtj6hee6dz9"}], "disc_number": 1, "duration_ms": 227280, "explicit": false, "external_ids": {"isrc": "USUM70602421"}, "external_urls": {"spotify": "https://open.spotify.com/track/4SJvGSZwtcIvA1feeXI9Ct"}, "href": "https://api.spotify.com/v1/tracks/4SJvGSZwtcIvA1feeXI9Ct", "id": "4SJvGSZwtcIvA1feeXI9Ct", "is_local": false, "is_playable": true, "name": "Pam Pam", "popularity": 0, "preview_url": null, "track_number": 22, "type": "track", "uri": "spotify:track:4SJvGSZwtcIvA1feeXI9Ct"}, {"album": {"album_type": "album", "artists": [{"external_urls": {"spotify": "https://open.spotify.com/artist/0LyfQWJT6nXafLPZqxe9Of"}, "href": "https://api.spotify.com/v1/artists/0LyfQWJT6nXafLPZqxe9Of", "id": "0LyfQWJT6nXafLPZqxe9Of", "name": "Various Artists", "type": "artist", "uri": "spotify:artist:0LyfQWJT6nXafLPZqxe9Of"}], "external_urls": {"spotify": "https://open.spotify.com/album/51aAVCjiLYzBGLNyKcp7y0"}, "href": "https://api.spotify.com/v1/albums/51aAVCjiLYzBGLNyKcp7y0", "id": "51aAVCjiLYzBGLNyKcp7y0", "images": [{"height": 640, "url": "https://i.scdn.co/image/ab67616d0000b27350da2395a47c74dcecdefba3", "width": 640}, {"height": 300, "url": "https://i.scdn.co/image/ab67616d00001e0250da2395a47c74dcecdefba3", "width": 300}, {"height": 64, "url": "https://i.scdn.co/image/ab67616d0000485150da2395a47c74dcecdefba3", "width": 64}], "name": "Saturday Night Latin Party", "release_date": "2022-02-25", "release_date_precision": "day", "total_tracks": 62, "type": "album", "uri": "spotify:album:51aAVCjiLYzBGLNyKcp7y0"}, "artists": [{"external_urls": {"spotify": "https://open.spotify.com/artist/1wZtkThiXbVNtj6hee6dz9"}, "href": "https://api.spotify.com/v1/artists/1wZtkThiXbVNtj6hee6dz9", "id": "1wZtkThiXbVNtj6hee6dz9", "name": "Wisin & Yandel", "type": "artist", "uri": "spotify:artist:1wZtkThiXbVNtj6hee6dz9"}], "disc_number": 1, "duration_ms": 227280, "explicit": false, "external_ids": {"isrc": "USUM70602421"}, "external_urls": {"spotify": "https://open.spotify.com/track/62AGJHxOvgScv6WM2nVCu8"}, "href": "https://api.spotify.com/v1/tracks/62AGJHxOvgScv6WM2nVCu8", "id": "62AGJHxOvgScv6WM2nVCu8", "is_local": false, "is_playable": true, "name": "Pam Pam", "popularity": 0, "preview_url": null, "track_number": 59, "type": "track", "uri": "spotify:track:62AGJHxOvgScv6WM2nVCu8"}, {"album": {"album_type": "compilation", "artists": [{"external_urls": {"spotify": "https://open.spotify.com/artist/0LyfQWJT6nXafLPZqxe9Of"}, "href": "https://api.spotify.com/v1/artists/0LyfQWJT6nXafLPZqxe9Of", "id": "0LyfQWJT6nXafLPZqxe9Of", "name": "Various Artists", "type": "artist", "uri": "spotify:artist:0LyfQWJT6nXafLPZqxe9Of"}], "external_urls": {"spotify": "https://open.spotify.com/album/2Lq78nM1NuI27xUqSzl68j"}, "href": "https://api.spotify.com/v1/albums/2Lq78nM1NuI27xUqSzl68j", "id": "2Lq78nM1NuI27xUqSzl68j", "images": [{"height": 640, "url": "https://i.scdn.co/image/ab67616d0000b2737808d62b9e4f1c5dce15f307", "width": 640}, {"height": 300, "url": "https://i.scdn.co/image/ab67616d00001e027808d62b9e4f1c5dce15f307", "width": 300}, {"height": 64, "url": "https://i.scdn.co/image/ab67616d000048517808d62b9e4f1c5dce15f307", "width": 64}], "name": "Bailoteo Gal\u00e1ctico", "release_date": "2022-02-23", "release_date_precision": "day", "total_tracks": 30, "type": "album", "uri": "spotify:album:2Lq78nM1NuI27xUqSzl68j"}, "artists": [{"external_urls": {"spotify": "https://open.spotify.com/artist/1wZtkThiXbVNtj6hee6dz9"}, "href": "https://api.spotify.com/v1/artists/1wZtkThiXbVNtj6hee6dz9", "id": "1wZtkThiXbVNtj6hee6dz9", "name": "Wisin & Yandel", "type": "artist", "uri": "spotify:artist:1wZtkThiXbVNtj6hee6dz9"}], "disc_number": 1, "duration_ms": 227280, "explicit": false, "external_ids": {"isrc": "USUM70602421"}, "external_urls": {"spotify": "https://open.spotify.com/track/4R0TO0dsw4NQLUgKDKGqWe"}, "href": "https://api.spotify.com/v1/tracks/4R0TO0dsw4NQLUgKDKGqWe", "id": "4R0TO0dsw4NQLUgKDKGqWe", "is_local": false, "is_playable": true, "name": "Pam Pam", "popularity": 0, "preview_url": null, "track_number": 3, "type": "track", "uri": "spotify:track:4R0TO0dsw4NQLUgKDKGqWe"}, {"album": {"album_type": "album", "artists": [{"external_urls": {"spotify": "https://open.spotify.com/artist/0LyfQWJT6nXafLPZqxe9Of"}, "href": "https://api.spotify.com/v1/artists/0LyfQWJT6nXafLPZqxe9Of", "id": "0LyfQWJT6nXafLPZqxe9Of", "name": "Various Artists", "type": "artist", "uri": "spotify:artist:0LyfQWJT6nXafLPZqxe9Of"}], "external_urls": {"spotify": "https://open.spotify.com/album/68CoUeC75QFgYUKaCASzCM"}, "href": "https://api.spotify.com/v1/albums/68CoUeC75QFgYUKaCASzCM", "id": "68CoUeC75QFgYUKaCASzCM", "images": [{"height": 640, "url": "https://i.scdn.co/image/ab67616d0000b273a97150c9525522343d5c018b", "width": 640}, {"height": 300, "url": "https://i.scdn.co/image/ab67616d00001e02a97150c9525522343d5c018b", "width": 300}, {"height": 64, "url": "https://i.scdn.co/image/ab67616d00004851a97150c9525522343d5c018b", "width": 64}], "name": "Fiesta Latina Monumental Vol. 2", "release_date": "2022-02-21", "release_date_precision": "day", "total_tracks": 24, "type": "album", "uri": "spotify:album:68CoUeC75QFgYUKaCASzCM"}, "artists": [{"external_urls": {"spotify": "https://open.spotify.com/artist/1wZtkThiXbVNtj6hee6dz9"}, "href": "https://api.spotify.com/v1/artists/1wZtkThiXbVNtj6hee6dz9", "id": "1wZtkThiXbVNtj6hee6dz9", "name": "Wisin & Yandel", "type": "artist", "uri": "spotify:artist:1wZtkThiXbVNtj6hee6dz9"}], "disc_number": 1, "duration_ms": 227280, "explicit": false, "external_ids": {"isrc": "USUM70602421"}, "external_urls": {"spotify": "https://open.spotify.com/track/45kclsbfuv4fiYUqeNissW"}, "href": "https://api.spotify.com/v1/tracks/45kclsbfuv4fiYUqeNissW", "id": "45kclsbfuv4fiYUqeNissW", "is_local": false, "is_playable": true, "name": "Pam Pam", "popularity": 0, "preview_url": null, "track_number": 19, "type": "track", "uri": "spotify:track:45kclsbfuv4fiYUqeNissW"}, {"album": {"album_type": "album", "artists": [{"external_urls": {"spotify": "https://open.spotify.com/artist/0LyfQWJT6nXafLPZqxe9Of"}, "href": "https://api.spotify.com/v1/artists/0LyfQWJT6nXafLPZqxe9Of", "id": "0LyfQWJT6nXafLPZqxe9Of", "name": "Various Artists", "type": "artist", "uri": "spotify:artist:0LyfQWJT6nXafLPZqxe9Of"}], "external_urls": {"spotify": "https://open.spotify.com/album/4cum3D7wjLsWMBwwKaUUKj"}, "href": "https://api.spotify.com/v1/albums/4cum3D7wjLsWMBwwKaUUKj", "id": "4cum3D7wjLsWMBwwKaUUKj", "images": [{"height": 640, "url": "https://i.scdn.co/image/ab67616d0000b273b99e2204e592086fbdfc043f", "width": 640}, {"height": 300, "url": "https://i.scdn.co/image/ab67616d00001e02b99e2204e592086fbdfc043f", "width": 300}, {"height": 64, "url": "https://i.scdn.co/image/ab67616d00004851b99e2204e592086fbdfc043f", "width": 64}], "name": "Reggaeton Sensible Vol. 2", "release_date": "2022-02-25", "release_date_precision": "day", "total_tracks": 25, "type": "album", "uri": "spotify:album:4cum3D7wjLsWMBwwKaUUKj"}, "artists": [{"external_urls": {"spotify": "https://open.spotify.com/artist/1wZtkThiXbVNtj6hee6dz9"}, "href": "https://api.spotify.com/v1/artists/1wZtkThiXbVNtj6hee6dz9", "id": "1wZtkThiXbVNtj6hee6dz9", "name": "Wisin & Yandel", "type": "artist", "uri": "spotify:artist:1wZtkThiXbVNtj6hee6dz9"}], "disc_number": 1, "duration_ms": 234546, "explicit": false, "external_ids": {"isrc": "USUM70614082"}, "external_urls": {"spotify": "https://open.spotify.com/track/6grQ9LDTRLUHEjA8orBnKn"}, "href": "https://api.spotify.com/v1/tracks/6grQ9LDTRLUHEjA8orBnKn", "id": "6grQ9LDTRLUHEjA8orBnKn", "is_local": false, "is_playable": true, "name": "Pegao", "popularity": 0, "preview_url": null, "track_number": 12, "type": "track", "uri": "spotify:track:6grQ9LDTRLUHEjA8orBnKn"}, {"album": {"album_type": "album", "artists": [{"external_urls": {"spotify": "https://open.spotify.com/artist/0LyfQWJT6nXafLPZqxe9Of"}, "href": "https://api.spotify.com/v1/artists/0LyfQWJT6nXafLPZqxe9Of", "id": "0LyfQWJT6nXafLPZqxe9Of", "name": "Various Artists", "type": "artist", "uri": "spotify:artist:0LyfQWJT6nXafLPZqxe9Of"}], "external_urls": {"spotify": "https://open.spotify.com/album/3SfVNctvNNqRiwzZz3Ipz9"}, "href": "https://api.spotify.com/v1/albums/3SfVNctvNNqRiwzZz3Ipz9", "id": "3SfVNctvNNqRiwzZz3Ipz9", "images": [{"height": 640, "url": "https://i.scdn.co/image/ab67616d0000b273b7e452b8fca0bb24c35f6299", "width": 640}, {"height": 300, "url": "https://i.scdn.co/image/ab67616d00001e02b7e452b8fca0bb24c35f6299", "width": 300}, {"height": 64, "url": "https://i.scdn.co/image/ab67616d00004851b7e452b8fca0bb24c35f6299", "width": 64}], "name": "Nochecita Urbana", "release_date": "2022-03-01", "release_date_precision": "day", "total_tracks": 30, "type": "album", "uri": "spotify:album:3SfVNctvNNqRiwzZz3Ipz9"}, "artists": [{"external_urls": {"spotify": "https://open.spotify.com/artist/1wZtkThiXbVNtj6hee6dz9"}, "href": "https://api.spotify.com/v1/artists/1wZtkThiXbVNtj6hee6dz9", "id": "1wZtkThiXbVNtj6hee6dz9", "name": "Wisin & Yandel", "type": "artist", "uri": "spotify:artist:1wZtkThiXbVNtj6hee6dz9"}], "disc_number": 1, "duration_ms": 259066, "explicit": false, "external_ids": {"isrc": "USUM70998449"}, "external_urls": {"spotify": "https://open.spotify.com/track/06MW7sm9IBZ7ZmFP4BzfSI"}, "href": "https://api.spotify.com/v1/tracks/06MW7sm9IBZ7ZmFP4BzfSI", "id": "06MW7sm9IBZ7ZmFP4BzfSI", "is_local": false, "is_playable": true, "name": "Te Siento", "popularity": 0, "preview_url": null, "track_number": 13, "type": "track", "uri": "spotify:track:06MW7sm9IBZ7ZmFP4BzfSI"}, {"album": {"album_type": "album", "artists": [{"external_urls": {"spotify": "https://open.spotify.com/artist/0LyfQWJT6nXafLPZqxe9Of"}, "href": "https://api.spotify.com/v1/artists/0LyfQWJT6nXafLPZqxe9Of", "id": "0LyfQWJT6nXafLPZqxe9Of", "name": "Various Artists", "type": "artist", "uri": "spotify:artist:0LyfQWJT6nXafLPZqxe9Of"}], "external_urls": {"spotify": "https://open.spotify.com/album/4WDRDad9ws4RcFYn2dCZsL"}, "href": "https://api.spotify.com/v1/albums/4WDRDad9ws4RcFYn2dCZsL", "id": "4WDRDad9ws4RcFYn2dCZsL", "images": [{"height": 640, "url": "https://i.scdn.co/image/ab67616d0000b273ab6b89dee7aa811268f118f7", "width": 640}, {"height": 300, "url": "https://i.scdn.co/image/ab67616d00001e02ab6b89dee7aa811268f118f7", "width": 300}, {"height": 64, "url": "https://i.scdn.co/image/ab67616d00004851ab6b89dee7aa811268f118f7", "width": 64}], "name": "Motivaci\u00f3n Total", "release_date": "2022-03-01", "release_date_precision": "day", "total_tracks": 40, "type": "album", "uri": "spotify:album:4WDRDad9ws4RcFYn2dCZsL"}, "artists": [{"external_urls": {"spotify": "https://open.spotify.com/artist/1wZtkThiXbVNtj6hee6dz9"}, "href": "https://api.spotify.com/v1/artists/1wZtkThiXbVNtj6hee6dz9", "id": "1wZtkThiXbVNtj6hee6dz9", "name": "Wisin & Yandel", "type": "artist", "uri": "spotify:artist:1wZtkThiXbVNtj6hee6dz9"}], "disc_number": 1, "duration_ms": 207186, "explicit": false, "external_ids": {"isrc": "USUM70756397"}, "external_urls": {"spotify": "https://open.spotify.com/track/2wgAb442a6uvzi1G2UHP02"}, "href": "https://api.spotify.com/v1/tracks/2wgAb442a6uvzi1G2UHP02", "id": "2wgAb442a6uvzi1G2UHP02", "is_local": false, "is_playable": true, "name": "Ahora Es", "popularity": 0, "preview_url": null, "track_number": 12, "type": "track", "uri": "spotify:track:2wgAb442a6uvzi1G2UHP02"}, {"album": {"album_type": "album", "artists": [{"external_urls": {"spotify": "https://open.spotify.com/artist/0LyfQWJT6nXafLPZqxe9Of"}, "href": "https://api.spotify.com/v1/artists/0LyfQWJT6nXafLPZqxe9Of", "id": "0LyfQWJT6nXafLPZqxe9Of", "name": "Various Artists", "type": "artist", "uri": "spotify:artist:0LyfQWJT6nXafLPZqxe9Of"}], "external_urls": {"spotify": "https://open.spotify.com/album/64tEBxiOfQ3bULSN91cTsP"}, "href": "https://api.spotify.com/v1/albums/64tEBxiOfQ3bULSN91cTsP", "id": "64tEBxiOfQ3bULSN91cTsP", "images": [{"height": 640, "url": "https://i.scdn.co/image/ab67616d0000b273a84d0a814058c2dad7d3292d", "width": 640}, {"height": 300, "url": "https://i.scdn.co/image/ab67616d00001e02a84d0a814058c2dad7d3292d", "width": 300}, {"height": 64, "url": "https://i.scdn.co/image/ab67616d00004851a84d0a814058c2dad7d3292d", "width": 64}], "name": "Vibras Fiesteras", "release_date": "2022-03-04", "release_date_precision": "day", "total_tracks": 38, "type": "album", "uri": "spotify:album:64tEBxiOfQ3bULSN91cTsP"}, "artists": [{"external_urls": {"spotify": "https://open.spotify.com/artist/1wZtkThiXbVNtj6hee6dz9"}, "href": "https://api.spotify.com/v1/artists/1wZtkThiXbVNtj6hee6dz9", "id": "1wZtkThiXbVNtj6hee6dz9", "name": "Wisin & Yandel", "type": "artist", "uri": "spotify:artist:1wZtkThiXbVNtj6hee6dz9"}], "disc_number": 1, "duration_ms": 227280, "explicit": false, "external_ids": {"isrc": "USUM70602421"}, "external_urls": {"spotify": "https://open.spotify.com/track/6cbwMueAQOzfJXSoW3tgIC"}, "href": "https://api.spotify.com/v1/tracks/6cbwMueAQOzfJXSoW3tgIC", "id": "6cbwMueAQOzfJXSoW3tgIC", "is_local": false, "is_playable": true, "name": "Pam Pam", "popularity": 0, "preview_url": null, "track_number": 4, "type": "track", "uri": "spotify:track:6cbwMueAQOzfJXSoW3tgIC"}, {"album": {"album_type": "album", "artists": [{"external_urls": {"spotify": "https://open.spotify.com/artist/0LyfQWJT6nXafLPZqxe9Of"}, "href": "https://api.spotify.com/v1/artists/0LyfQWJT6nXafLPZqxe9Of", "id": "0LyfQWJT6nXafLPZqxe9Of", "name": "Various Artists", "type": "artist", "uri": "spotify:artist:0LyfQWJT6nXafLPZqxe9Of"}], "external_urls": {"spotify": "https://open.spotify.com/album/1jHzt6K68TyKsJIRTRGL81"}, "href": "https://api.spotify.com/v1/albums/1jHzt6K68TyKsJIRTRGL81", "id": "1jHzt6K68TyKsJIRTRGL81", "images": [{"height": 640, "url": "https://i.scdn.co/image/ab67616d0000b273ca1b745afca302ca5e2303df", "width": 640}, {"height": 300, "url": "https://i.scdn.co/image/ab67616d00001e02ca1b745afca302ca5e2303df", "width": 300}, {"height": 64, "url": "https://i.scdn.co/image/ab67616d00004851ca1b745afca302ca5e2303df", "width": 64}], "name": "Puros Hits Latinos", "release_date": "2022-03-03", "release_date_precision": "day", "total_tracks": 40, "type": "album", "uri": "spotify:album:1jHzt6K68TyKsJIRTRGL81"}, "artists": [{"external_urls": {"spotify": "https://open.spotify.com/artist/1wZtkThiXbVNtj6hee6dz9"}, "href": "https://api.spotify.com/v1/artists/1wZtkThiXbVNtj6hee6dz9", "id": "1wZtkThiXbVNtj6hee6dz9", "name": "Wisin & Yandel", "type": "artist", "uri": "spotify:artist:1wZtkThiXbVNtj6hee6dz9"}, {"external_urls": {"spotify": "https://open.spotify.com/artist/33ScadVnbm2X8kkUqOkC6Z"}, "href": "https://api.spotify.com/v1/artists/33ScadVnbm2X8kkUqOkC6Z", "id": "33ScadVnbm2X8kkUqOkC6Z", "name": "Don Omar", "type": "artist", "uri": "spotify:artist:33ScadVnbm2X8kkUqOkC6Z"}], "disc_number": 1, "duration_ms": 223266, "explicit": false, "external_ids": {"isrc": "USUM70614167"}, "external_urls": {"spotify": "https://open.spotify.com/track/4AwRbIQu3fhEHKnZbbbQGF"}, "href": "https://api.spotify.com/v1/tracks/4AwRbIQu3fhEHKnZbbbQGF", "id": "4AwRbIQu3fhEHKnZbbbQGF", "is_local": false, "is_playable": true, "name": "Nadie Como Tu", "popularity": 0, "preview_url": null, "track_number": 29, "type": "track", "uri": "spotify:track:4AwRbIQu3fhEHKnZbbbQGF"}, {"album": {"album_type": "album", "artists": [{"external_urls": {"spotify": "https://open.spotify.com/artist/0LyfQWJT6nXafLPZqxe9Of"}, "href": "https://api.spotify.com/v1/artists/0LyfQWJT6nXafLPZqxe9Of", "id": "0LyfQWJT6nXafLPZqxe9Of", "name": "Various Artists", "type": "artist", "uri": "spotify:artist:0LyfQWJT6nXafLPZqxe9Of"}], "external_urls": {"spotify": "https://open.spotify.com/album/0p1XEYtBpP3vIGKQAzGNbi"}, "href": "https://api.spotify.com/v1/albums/0p1XEYtBpP3vIGKQAzGNbi", "id": "0p1XEYtBpP3vIGKQAzGNbi", "images": [{"height": 640, "url": "https://i.scdn.co/image/ab67616d0000b273a1c2a037ecdf76153666d83c", "width": 640}, {"height": 300, "url": "https://i.scdn.co/image/ab67616d00001e02a1c2a037ecdf76153666d83c", "width": 300}, {"height": 64, "url": "https://i.scdn.co/image/ab67616d00004851a1c2a037ecdf76153666d83c", "width": 64}], "name": "Radar Fiestero", "release_date": "2022-03-02", "release_date_precision": "day", "total_tracks": 40, "type": "album", "uri": "spotify:album:0p1XEYtBpP3vIGKQAzGNbi"}, "artists": [{"external_urls": {"spotify": "https://open.spotify.com/artist/1wZtkThiXbVNtj6hee6dz9"}, "href": "https://api.spotify.com/v1/artists/1wZtkThiXbVNtj6hee6dz9", "id": "1wZtkThiXbVNtj6hee6dz9", "name": "Wisin & Yandel", "type": "artist", "uri": "spotify:artist:1wZtkThiXbVNtj6hee6dz9"}], "disc_number": 1, "duration_ms": 234546, "explicit": false, "external_ids": {"isrc": "USUM70614082"}, "external_urls": {"spotify": "https://open.spotify.com/track/4MlSaAKbDEvhfTQN02j9va"}, "href": "https://api.spotify.com/v1/tracks/4MlSaAKbDEvhfTQN02j9va", "id": "4MlSaAKbDEvhfTQN02j9va", "is_local": false, "is_playable": true, "name": "Pegao", "popularity": 0, "preview_url": null, "track_number": 24, "type": "track", "uri": "spotify:track:4MlSaAKbDEvhfTQN02j9va"}, {"album": {"album_type": "album", "artists": [{"external_urls": {"spotify": "https://open.spotify.com/artist/0LyfQWJT6nXafLPZqxe9Of"}, "href": "https://api.spotify.com/v1/artists/0LyfQWJT6nXafLPZqxe9Of", "id": "0LyfQWJT6nXafLPZqxe9Of", "name": "Various Artists", "type": "artist", "uri": "spotify:artist:0LyfQWJT6nXafLPZqxe9Of"}], "external_urls": {"spotify": "https://open.spotify.com/album/0p1XEYtBpP3vIGKQAzGNbi"}, "href": "https://api.spotify.com/v1/albums/0p1XEYtBpP3vIGKQAzGNbi", "id": "0p1XEYtBpP3vIGKQAzGNbi", "images": [{"height": 640, "url": "https://i.scdn.co/image/ab67616d0000b273a1c2a037ecdf76153666d83c", "width": 640}, {"height": 300, "url": "https://i.scdn.co/image/ab67616d00001e02a1c2a037ecdf76153666d83c", "width": 300}, {"height": 64, "url": "https://i.scdn.co/image/ab67616d00004851a1c2a037ecdf76153666d83c", "width": 64}], "name": "Radar Fiestero", "release_date": "2022-03-02", "release_date_precision": "day", "total_tracks": 40, "type": "album", "uri": "spotify:album:0p1XEYtBpP3vIGKQAzGNbi"}, "artists": [{"external_urls": {"spotify": "https://open.spotify.com/artist/1wZtkThiXbVNtj6hee6dz9"}, "href": "https://api.spotify.com/v1/artists/1wZtkThiXbVNtj6hee6dz9", "id": "1wZtkThiXbVNtj6hee6dz9", "name": "Wisin & Yandel", "type": "artist", "uri": "spotify:artist:1wZtkThiXbVNtj6hee6dz9"}], "disc_number": 1, "duration_ms": 264773, "explicit": false, "external_ids": {"isrc": "USUM70963612"}, "external_urls": {"spotify": "https://open.spotify.com/track/293bodh8vvfJtWjvQUre0g"}, "href": "https://api.spotify.com/v1/tracks/293bodh8vvfJtWjvQUre0g", "id": "293bodh8vvfJtWjvQUre0g", "is_local": false, "is_playable": true, "name": "Besos Mojados", "popularity": 0, "preview_url": null, "track_number": 6, "type": "track", "uri": "spotify:track:293bodh8vvfJtWjvQUre0g"}, {"album": {"album_type": "album", "artists": [{"external_urls": {"spotify": "https://open.spotify.com/artist/0LyfQWJT6nXafLPZqxe9Of"}, "href": "https://api.spotify.com/v1/artists/0LyfQWJT6nXafLPZqxe9Of", "id": "0LyfQWJT6nXafLPZqxe9Of", "name": "Various Artists", "type": "artist", "uri": "spotify:artist:0LyfQWJT6nXafLPZqxe9Of"}], "external_urls": {"spotify": "https://open.spotify.com/album/6M90Z1naE1w2S6lS7GJN3e"}, "href": "https://api.spotify.com/v1/albums/6M90Z1naE1w2S6lS7GJN3e", "id": "6M90Z1naE1w2S6lS7GJN3e", "images": [{"height": 640, "url": "https://i.scdn.co/image/ab67616d0000b273b799837cae627297a38d2003", "width": 640}, {"height": 300, "url": "https://i.scdn.co/image/ab67616d00001e02b799837cae627297a38d2003", "width": 300}, {"height": 64, "url": "https://i.scdn.co/image/ab67616d00004851b799837cae627297a38d2003", "width": 64}], "name": "Tardecitas Lluviosas", "release_date": "2022-03-04", "release_date_precision": "day", "total_tracks": 40, "type": "album", "uri": "spotify:album:6M90Z1naE1w2S6lS7GJN3e"}, "artists": [{"external_urls": {"spotify": "https://open.spotify.com/artist/1wZtkThiXbVNtj6hee6dz9"}, "href": "https://api.spotify.com/v1/artists/1wZtkThiXbVNtj6hee6dz9", "id": "1wZtkThiXbVNtj6hee6dz9", "name": "Wisin & Yandel", "type": "artist", "uri": "spotify:artist:1wZtkThiXbVNtj6hee6dz9"}], "disc_number": 1, "duration_ms": 207306, "explicit": false, "external_ids": {"isrc": "USUM70614172"}, "external_urls": {"spotify": "https://open.spotify.com/track/0qGhrtdmADYmQV8F9iOVP8"}, "href": "https://api.spotify.com/v1/tracks/0qGhrtdmADYmQV8F9iOVP8", "id": "0qGhrtdmADYmQV8F9iOVP8", "is_local": false, "is_playable": true, "name": "Yo Te Quiero", "popularity": 0, "preview_url": null, "track_number": 6, "type": "track", "uri": "spotify:track:0qGhrtdmADYmQV8F9iOVP8"}, {"album": {"album_type": "album", "artists": [{"external_urls": {"spotify": "https://open.spotify.com/artist/0LyfQWJT6nXafLPZqxe9Of"}, "href": "https://api.spotify.com/v1/artists/0LyfQWJT6nXafLPZqxe9Of", "id": "0LyfQWJT6nXafLPZqxe9Of", "name": "Various Artists", "type": "artist", "uri": "spotify:artist:0LyfQWJT6nXafLPZqxe9Of"}], "external_urls": {"spotify": "https://open.spotify.com/album/3wmNbM9MJrG7kdjTeM6SQC"}, "href": "https://api.spotify.com/v1/albums/3wmNbM9MJrG7kdjTeM6SQC", "id": "3wmNbM9MJrG7kdjTeM6SQC", "images": [{"height": 640, "url": "https://i.scdn.co/image/ab67616d0000b273b9588e652f414155fc719704", "width": 640}, {"height": 300, "url": "https://i.scdn.co/image/ab67616d00001e02b9588e652f414155fc719704", "width": 300}, {"height": 64, "url": "https://i.scdn.co/image/ab67616d00004851b9588e652f414155fc719704", "width": 64}], "name": "Perreo Para Acampar Vol. 4", "release_date": "2022-02-26", "release_date_precision": "day", "total_tracks": 24, "type": "album", "uri": "spotify:album:3wmNbM9MJrG7kdjTeM6SQC"}, "artists": [{"external_urls": {"spotify": "https://open.spotify.com/artist/1wZtkThiXbVNtj6hee6dz9"}, "href": "https://api.spotify.com/v1/artists/1wZtkThiXbVNtj6hee6dz9", "id": "1wZtkThiXbVNtj6hee6dz9", "name": "Wisin & Yandel", "type": "artist", "uri": "spotify:artist:1wZtkThiXbVNtj6hee6dz9"}], "disc_number": 1, "duration_ms": 180386, "explicit": false, "external_ids": {"isrc": "USUM70963610"}, "external_urls": {"spotify": "https://open.spotify.com/track/2wnn47xTwQDyfTjiP1LxgC"}, "href": "https://api.spotify.com/v1/tracks/2wnn47xTwQDyfTjiP1LxgC", "id": "2wnn47xTwQDyfTjiP1LxgC", "is_local": false, "is_playable": true, "name": "Abusadora", "popularity": 0, "preview_url": null, "track_number": 1, "type": "track", "uri": "spotify:track:2wnn47xTwQDyfTjiP1LxgC"}, {"album": {"album_type": "album", "artists": [{"external_urls": {"spotify": "https://open.spotify.com/artist/0LyfQWJT6nXafLPZqxe9Of"}, "href": "https://api.spotify.com/v1/artists/0LyfQWJT6nXafLPZqxe9Of", "id": "0LyfQWJT6nXafLPZqxe9Of", "name": "Various Artists", "type": "artist", "uri": "spotify:artist:0LyfQWJT6nXafLPZqxe9Of"}], "external_urls": {"spotify": "https://open.spotify.com/album/5oM8838HkpSa2roJSpOO4Q"}, "href": "https://api.spotify.com/v1/albums/5oM8838HkpSa2roJSpOO4Q", "id": "5oM8838HkpSa2roJSpOO4Q", "images": [{"height": 640, "url": "https://i.scdn.co/image/ab67616d0000b27321e06a6fc661430d1a7700d7", "width": 640}, {"height": 300, "url": "https://i.scdn.co/image/ab67616d00001e0221e06a6fc661430d1a7700d7", "width": 300}, {"height": 64, "url": "https://i.scdn.co/image/ab67616d0000485121e06a6fc661430d1a7700d7", "width": 64}], "name": "Finde Urbano", "release_date": "2022-02-22", "release_date_precision": "day", "total_tracks": 45, "type": "album", "uri": "spotify:album:5oM8838HkpSa2roJSpOO4Q"}, "artists": [{"external_urls": {"spotify": "https://open.spotify.com/artist/1wZtkThiXbVNtj6hee6dz9"}, "href": "https://api.spotify.com/v1/artists/1wZtkThiXbVNtj6hee6dz9", "id": "1wZtkThiXbVNtj6hee6dz9", "name": "Wisin & Yandel", "type": "artist", "uri": "spotify:artist:1wZtkThiXbVNtj6hee6dz9"}], "disc_number": 1, "duration_ms": 259066, "explicit": false, "external_ids": {"isrc": "USUM70998449"}, "external_urls": {"spotify": "https://open.spotify.com/track/1GLISincKBNN3oSJxQkGMT"}, "href": "https://api.spotify.com/v1/tracks/1GLISincKBNN3oSJxQkGMT", "id": "1GLISincKBNN3oSJxQkGMT", "is_local": false, "is_playable": true, "name": "Te Siento", "popularity": 1, "preview_url": null, "track_number": 38, "type": "track", "uri": "spotify:track:1GLISincKBNN3oSJxQkGMT"}, {"album": {"album_type": "album", "artists": [{"external_urls": {"spotify": "https://open.spotify.com/artist/0LyfQWJT6nXafLPZqxe9Of"}, "href": "https://api.spotify.com/v1/artists/0LyfQWJT6nXafLPZqxe9Of", "id": "0LyfQWJT6nXafLPZqxe9Of", "name": "Various Artists", "type": "artist", "uri": "spotify:artist:0LyfQWJT6nXafLPZqxe9Of"}], "external_urls": {"spotify": "https://open.spotify.com/album/51vGUl8EDS3LbnWdFcNegs"}, "href": "https://api.spotify.com/v1/albums/51vGUl8EDS3LbnWdFcNegs", "id": "51vGUl8EDS3LbnWdFcNegs", "images": [{"height": 640, "url": "https://i.scdn.co/image/ab67616d0000b273b4f8979343f0388c71050ace", "width": 640}, {"height": 300, "url": "https://i.scdn.co/image/ab67616d00001e02b4f8979343f0388c71050ace", "width": 300}, {"height": 64, "url": "https://i.scdn.co/image/ab67616d00004851b4f8979343f0388c71050ace", "width": 64}], "name": "Muchos Temazos", "release_date": "2022-03-01", "release_date_precision": "day", "total_tracks": 30, "type": "album", "uri": "spotify:album:51vGUl8EDS3LbnWdFcNegs"}, "artists": [{"external_urls": {"spotify": "https://open.spotify.com/artist/1wZtkThiXbVNtj6hee6dz9"}, "href": "https://api.spotify.com/v1/artists/1wZtkThiXbVNtj6hee6dz9", "id": "1wZtkThiXbVNtj6hee6dz9", "name": "Wisin & Yandel", "type": "artist", "uri": "spotify:artist:1wZtkThiXbVNtj6hee6dz9"}], "disc_number": 1, "duration_ms": 259066, "explicit": false, "external_ids": {"isrc": "USUM70998449"}, "external_urls": {"spotify": "https://open.spotify.com/track/3QMmOqGUHjjkkeuvZKmser"}, "href": "https://api.spotify.com/v1/tracks/3QMmOqGUHjjkkeuvZKmser", "id": "3QMmOqGUHjjkkeuvZKmser", "is_local": false, "is_playable": true, "name": "Te Siento", "popularity": 1, "preview_url": null, "track_number": 27, "type": "track", "uri": "spotify:track:3QMmOqGUHjjkkeuvZKmser"}, {"album": {"album_type": "album", "artists": [{"external_urls": {"spotify": "https://open.spotify.com/artist/0LyfQWJT6nXafLPZqxe9Of"}, "href": "https://api.spotify.com/v1/artists/0LyfQWJT6nXafLPZqxe9Of", "id": "0LyfQWJT6nXafLPZqxe9Of", "name": "Various Artists", "type": "artist", "uri": "spotify:artist:0LyfQWJT6nXafLPZqxe9Of"}], "external_urls": {"spotify": "https://open.spotify.com/album/5xLEcb5yicYFvqYjO15cM0"}, "href": "https://api.spotify.com/v1/albums/5xLEcb5yicYFvqYjO15cM0", "id": "5xLEcb5yicYFvqYjO15cM0", "images": [{"height": 640, "url": "https://i.scdn.co/image/ab67616d0000b2733c5671f90b8ba8ebc858dea6", "width": 640}, {"height": 300, "url": "https://i.scdn.co/image/ab67616d00001e023c5671f90b8ba8ebc858dea6", "width": 300}, {"height": 64, "url": "https://i.scdn.co/image/ab67616d000048513c5671f90b8ba8ebc858dea6", "width": 64}], "name": "\u00c9xitos Ardientes", "release_date": "2022-03-04", "release_date_precision": "day", "total_tracks": 40, "type": "album", "uri": "spotify:album:5xLEcb5yicYFvqYjO15cM0"}, "artists": [{"external_urls": {"spotify": "https://open.spotify.com/artist/1wZtkThiXbVNtj6hee6dz9"}, "href": "https://api.spotify.com/v1/artists/1wZtkThiXbVNtj6hee6dz9", "id": "1wZtkThiXbVNtj6hee6dz9", "name": "Wisin & Yandel", "type": "artist", "uri": "spotify:artist:1wZtkThiXbVNtj6hee6dz9"}], "disc_number": 1, "duration_ms": 246853, "explicit": false, "external_ids": {"isrc": "USUM71029769"}, "external_urls": {"spotify": "https://open.spotify.com/track/63bzXXc5s5mNCjMIfgheSb"}, "href": "https://api.spotify.com/v1/tracks/63bzXXc5s5mNCjMIfgheSb", "id": "63bzXXc5s5mNCjMIfgheSb", "is_local": false, "is_playable": true, "name": "Tu Olor", "popularity": 0, "preview_url": null, "track_number": 13, "type": "track", "uri": "spotify:track:63bzXXc5s5mNCjMIfgheSb"}, {"album": {"album_type": "album", "artists": [{"external_urls": {"spotify": "https://open.spotify.com/artist/0LyfQWJT6nXafLPZqxe9Of"}, "href": "https://api.spotify.com/v1/artists/0LyfQWJT6nXafLPZqxe9Of", "id": "0LyfQWJT6nXafLPZqxe9Of", "name": "Various Artists", "type": "artist", "uri": "spotify:artist:0LyfQWJT6nXafLPZqxe9Of"}], "external_urls": {"spotify": "https://open.spotify.com/album/4Om2ao2cexnMspejNcM5WF"}, "href": "https://api.spotify.com/v1/albums/4Om2ao2cexnMspejNcM5WF", "id": "4Om2ao2cexnMspejNcM5WF", "images": [{"height": 640, "url": "https://i.scdn.co/image/ab67616d0000b273dd853e4e0ade60df8bd729bf", "width": 640}, {"height": 300, "url": "https://i.scdn.co/image/ab67616d00001e02dd853e4e0ade60df8bd729bf", "width": 300}, {"height": 64, "url": "https://i.scdn.co/image/ab67616d00004851dd853e4e0ade60df8bd729bf", "width": 64}], "name": "Perreo Deluxe", "release_date": "2022-03-02", "release_date_precision": "day", "total_tracks": 30, "type": "album", "uri": "spotify:album:4Om2ao2cexnMspejNcM5WF"}, "artists": [{"external_urls": {"spotify": "https://open.spotify.com/artist/1wZtkThiXbVNtj6hee6dz9"}, "href": "https://api.spotify.com/v1/artists/1wZtkThiXbVNtj6hee6dz9", "id": "1wZtkThiXbVNtj6hee6dz9", "name": "Wisin & Yandel", "type": "artist", "uri": "spotify:artist:1wZtkThiXbVNtj6hee6dz9"}], "disc_number": 1, "duration_ms": 207186, "explicit": false, "external_ids": {"isrc": "USUM70756397"}, "external_urls": {"spotify": "https://open.spotify.com/track/2UimaT8Q2JiJmHlGnugfFi"}, "href": "https://api.spotify.com/v1/tracks/2UimaT8Q2JiJmHlGnugfFi", "id": "2UimaT8Q2JiJmHlGnugfFi", "is_local": false, "is_playable": true, "name": "Ahora Es", "popularity": 0, "preview_url": null, "track_number": 11, "type": "track", "uri": "spotify:track:2UimaT8Q2JiJmHlGnugfFi"}, {"album": {"album_type": "album", "artists": [{"external_urls": {"spotify": "https://open.spotify.com/artist/0LyfQWJT6nXafLPZqxe9Of"}, "href": "https://api.spotify.com/v1/artists/0LyfQWJT6nXafLPZqxe9Of", "id": "0LyfQWJT6nXafLPZqxe9Of", "name": "Various Artists", "type": "artist", "uri": "spotify:artist:0LyfQWJT6nXafLPZqxe9Of"}], "external_urls": {"spotify": "https://open.spotify.com/album/3oRcXAFqlrH24ueHXL1iBq"}, "href": "https://api.spotify.com/v1/albums/3oRcXAFqlrH24ueHXL1iBq", "id": "3oRcXAFqlrH24ueHXL1iBq", "images": [{"height": 640, "url": "https://i.scdn.co/image/ab67616d0000b2737e302db77dcb6236d321b9e4", "width": 640}, {"height": 300, "url": "https://i.scdn.co/image/ab67616d00001e027e302db77dcb6236d321b9e4", "width": 300}, {"height": 64, "url": "https://i.scdn.co/image/ab67616d000048517e302db77dcb6236d321b9e4", "width": 64}], "name": "Mega Temazos", "release_date": "2022-02-28", "release_date_precision": "day", "total_tracks": 36, "type": "album", "uri": "spotify:album:3oRcXAFqlrH24ueHXL1iBq"}, "artists": [{"external_urls": {"spotify": "https://open.spotify.com/artist/1wZtkThiXbVNtj6hee6dz9"}, "href": "https://api.spotify.com/v1/artists/1wZtkThiXbVNtj6hee6dz9", "id": "1wZtkThiXbVNtj6hee6dz9", "name": "Wisin & Yandel", "type": "artist", "uri": "spotify:artist:1wZtkThiXbVNtj6hee6dz9"}], "disc_number": 1, "duration_ms": 227280, "explicit": false, "external_ids": {"isrc": "USUM70602421"}, "external_urls": {"spotify": "https://open.spotify.com/track/3HjV2ilAawvjebN1vJc6fd"}, "href": "https://api.spotify.com/v1/tracks/3HjV2ilAawvjebN1vJc6fd", "id": "3HjV2ilAawvjebN1vJc6fd", "is_local": false, "is_playable": true, "name": "Pam Pam", "popularity": 0, "preview_url": null, "track_number": 20, "type": "track", "uri": "spotify:track:3HjV2ilAawvjebN1vJc6fd"}, {"album": {"album_type": "album", "artists": [{"external_urls": {"spotify": "https://open.spotify.com/artist/0LyfQWJT6nXafLPZqxe9Of"}, "href": "https://api.spotify.com/v1/artists/0LyfQWJT6nXafLPZqxe9Of", "id": "0LyfQWJT6nXafLPZqxe9Of", "name": "Various Artists", "type": "artist", "uri": "spotify:artist:0LyfQWJT6nXafLPZqxe9Of"}], "external_urls": {"spotify": "https://open.spotify.com/album/3U9QTGfqfev9PbWeKtYTa4"}, "href": "https://api.spotify.com/v1/albums/3U9QTGfqfev9PbWeKtYTa4", "id": "3U9QTGfqfev9PbWeKtYTa4", "images": [{"height": 640, "url": "https://i.scdn.co/image/ab67616d0000b273d4a4cb928e11bd33925992db", "width": 640}, {"height": 300, "url": "https://i.scdn.co/image/ab67616d00001e02d4a4cb928e11bd33925992db", "width": 300}, {"height": 64, "url": "https://i.scdn.co/image/ab67616d00004851d4a4cb928e11bd33925992db", "width": 64}], "name": "Posada De Perreo Vol. 2", "release_date": "2022-02-28", "release_date_precision": "day", "total_tracks": 24, "type": "album", "uri": "spotify:album:3U9QTGfqfev9PbWeKtYTa4"}, "artists": [{"external_urls": {"spotify": "https://open.spotify.com/artist/1wZtkThiXbVNtj6hee6dz9"}, "href": "https://api.spotify.com/v1/artists/1wZtkThiXbVNtj6hee6dz9", "id": "1wZtkThiXbVNtj6hee6dz9", "name": "Wisin & Yandel", "type": "artist", "uri": "spotify:artist:1wZtkThiXbVNtj6hee6dz9"}], "disc_number": 1, "duration_ms": 271720, "explicit": false, "external_ids": {"isrc": "USUM71018815"}, "external_urls": {"spotify": "https://open.spotify.com/track/7hLtEL3NCdKKIdYL6MrfOM"}, "href": "https://api.spotify.com/v1/tracks/7hLtEL3NCdKKIdYL6MrfOM", "id": "7hLtEL3NCdKKIdYL6MrfOM", "is_local": false, "is_playable": true, "name": "Estoy Enamorado", "popularity": 0, "preview_url": null, "track_number": 21, "type": "track", "uri": "spotify:track:7hLtEL3NCdKKIdYL6MrfOM"}, {"album": {"album_type": "album", "artists": [{"external_urls": {"spotify": "https://open.spotify.com/artist/0LyfQWJT6nXafLPZqxe9Of"}, "href": "https://api.spotify.com/v1/artists/0LyfQWJT6nXafLPZqxe9Of", "id": "0LyfQWJT6nXafLPZqxe9Of", "name": "Various Artists", "type": "artist", "uri": "spotify:artist:0LyfQWJT6nXafLPZqxe9Of"}], "external_urls": {"spotify": "https://open.spotify.com/album/1edfs3Uev1mln0XGfH5RuK"}, "href": "https://api.spotify.com/v1/albums/1edfs3Uev1mln0XGfH5RuK", "id": "1edfs3Uev1mln0XGfH5RuK", "images": [{"height": 640, "url": "https://i.scdn.co/image/ab67616d0000b2730e6441c6d9f659350aaae924", "width": 640}, {"height": 300, "url": "https://i.scdn.co/image/ab67616d00001e020e6441c6d9f659350aaae924", "width": 300}, {"height": 64, "url": "https://i.scdn.co/image/ab67616d000048510e6441c6d9f659350aaae924", "width": 64}], "name": "S\u00e1bado Fiestero", "release_date": "2022-03-04", "release_date_precision": "day", "total_tracks": 40, "type": "album", "uri": "spotify:album:1edfs3Uev1mln0XGfH5RuK"}, "artists": [{"external_urls": {"spotify": "https://open.spotify.com/artist/1wZtkThiXbVNtj6hee6dz9"}, "href": "https://api.spotify.com/v1/artists/1wZtkThiXbVNtj6hee6dz9", "id": "1wZtkThiXbVNtj6hee6dz9", "name": "Wisin & Yandel", "type": "artist", "uri": "spotify:artist:1wZtkThiXbVNtj6hee6dz9"}], "disc_number": 1, "duration_ms": 234546, "explicit": false, "external_ids": {"isrc": "USUM70614082"}, "external_urls": {"spotify": "https://open.spotify.com/track/7E8nmaqb6gF98TtcbJ5Xq5"}, "href": "https://api.spotify.com/v1/tracks/7E8nmaqb6gF98TtcbJ5Xq5", "id": "7E8nmaqb6gF98TtcbJ5Xq5", "is_local": false, "is_playable": true, "name": "Pegao", "popularity": 0, "preview_url": null, "track_number": 34, "type": "track", "uri": "spotify:track:7E8nmaqb6gF98TtcbJ5Xq5"}, {"album": {"album_type": "album", "artists": [{"external_urls": {"spotify": "https://open.spotify.com/artist/0LyfQWJT6nXafLPZqxe9Of"}, "href": "https://api.spotify.com/v1/artists/0LyfQWJT6nXafLPZqxe9Of", "id": "0LyfQWJT6nXafLPZqxe9Of", "name": "Various Artists", "type": "artist", "uri": "spotify:artist:0LyfQWJT6nXafLPZqxe9Of"}], "external_urls": {"spotify": "https://open.spotify.com/album/3WeCCbuJ7ztcpS7A97UCrR"}, "href": "https://api.spotify.com/v1/albums/3WeCCbuJ7ztcpS7A97UCrR", "id": "3WeCCbuJ7ztcpS7A97UCrR", "images": [{"height": 640, "url": "https://i.scdn.co/image/ab67616d0000b2733b0e9b45eee4022b5b27c0e7", "width": 640}, {"height": 300, "url": "https://i.scdn.co/image/ab67616d00001e023b0e9b45eee4022b5b27c0e7", "width": 300}, {"height": 64, "url": "https://i.scdn.co/image/ab67616d000048513b0e9b45eee4022b5b27c0e7", "width": 64}], "name": "Divertido Reggaeton Vol. 1", "release_date": "2022-02-28", "release_date_precision": "day", "total_tracks": 21, "type": "album", "uri": "spotify:album:3WeCCbuJ7ztcpS7A97UCrR"}, "artists": [{"external_urls": {"spotify": "https://open.spotify.com/artist/1wZtkThiXbVNtj6hee6dz9"}, "href": "https://api.spotify.com/v1/artists/1wZtkThiXbVNtj6hee6dz9", "id": "1wZtkThiXbVNtj6hee6dz9", "name": "Wisin & Yandel", "type": "artist", "uri": "spotify:artist:1wZtkThiXbVNtj6hee6dz9"}], "disc_number": 1, "duration_ms": 271720, "explicit": false, "external_ids": {"isrc": "USUM71018815"}, "external_urls": {"spotify": "https://open.spotify.com/track/1VOUJCqpD0kmV8xk3gEpFi"}, "href": "https://api.spotify.com/v1/tracks/1VOUJCqpD0kmV8xk3gEpFi", "id": "1VOUJCqpD0kmV8xk3gEpFi", "is_local": false, "is_playable": true, "name": "Estoy Enamorado", "popularity": 0, "preview_url": null, "track_number": 4, "type": "track", "uri": "spotify:track:1VOUJCqpD0kmV8xk3gEpFi"}, {"album": {"album_type": "album", "artists": [{"external_urls": {"spotify": "https://open.spotify.com/artist/0LyfQWJT6nXafLPZqxe9Of"}, "href": "https://api.spotify.com/v1/artists/0LyfQWJT6nXafLPZqxe9Of", "id": "0LyfQWJT6nXafLPZqxe9Of", "name": "Various Artists", "type": "artist", "uri": "spotify:artist:0LyfQWJT6nXafLPZqxe9Of"}], "external_urls": {"spotify": "https://open.spotify.com/album/5FesL8IeeluHVy9J54xW4H"}, "href": "https://api.spotify.com/v1/albums/5FesL8IeeluHVy9J54xW4H", "id": "5FesL8IeeluHVy9J54xW4H", "images": [{"height": 640, "url": "https://i.scdn.co/image/ab67616d0000b2734e304760e423e87acff8282d", "width": 640}, {"height": 300, "url": "https://i.scdn.co/image/ab67616d00001e024e304760e423e87acff8282d", "width": 300}, {"height": 64, "url": "https://i.scdn.co/image/ab67616d000048514e304760e423e87acff8282d", "width": 64}], "name": "Sigue el Party", "release_date": "2022-02-18", "release_date_precision": "day", "total_tracks": 26, "type": "album", "uri": "spotify:album:5FesL8IeeluHVy9J54xW4H"}, "artists": [{"external_urls": {"spotify": "https://open.spotify.com/artist/1wZtkThiXbVNtj6hee6dz9"}, "href": "https://api.spotify.com/v1/artists/1wZtkThiXbVNtj6hee6dz9", "id": "1wZtkThiXbVNtj6hee6dz9", "name": "Wisin & Yandel", "type": "artist", "uri": "spotify:artist:1wZtkThiXbVNtj6hee6dz9"}], "disc_number": 1, "duration_ms": 227280, "explicit": false, "external_ids": {"isrc": "USUM70602421"}, "external_urls": {"spotify": "https://open.spotify.com/track/4TmiZKPdQm6mD2r9Oh1qRq"}, "href": "https://api.spotify.com/v1/tracks/4TmiZKPdQm6mD2r9Oh1qRq", "id": "4TmiZKPdQm6mD2r9Oh1qRq", "is_local": false, "is_playable": true, "name": "Pam Pam", "popularity": 0, "preview_url": null, "track_number": 6, "type": "track", "uri": "spotify:track:4TmiZKPdQm6mD2r9Oh1qRq"}, {"album": {"album_type": "album", "artists": [{"external_urls": {"spotify": "https://open.spotify.com/artist/0LyfQWJT6nXafLPZqxe9Of"}, "href": "https://api.spotify.com/v1/artists/0LyfQWJT6nXafLPZqxe9Of", "id": "0LyfQWJT6nXafLPZqxe9Of", "name": "Various Artists", "type": "artist", "uri": "spotify:artist:0LyfQWJT6nXafLPZqxe9Of"}], "external_urls": {"spotify": "https://open.spotify.com/album/4WDRDad9ws4RcFYn2dCZsL"}, "href": "https://api.spotify.com/v1/albums/4WDRDad9ws4RcFYn2dCZsL", "id": "4WDRDad9ws4RcFYn2dCZsL", "images": [{"height": 640, "url": "https://i.scdn.co/image/ab67616d0000b273ab6b89dee7aa811268f118f7", "width": 640}, {"height": 300, "url": "https://i.scdn.co/image/ab67616d00001e02ab6b89dee7aa811268f118f7", "width": 300}, {"height": 64, "url": "https://i.scdn.co/image/ab67616d00004851ab6b89dee7aa811268f118f7", "width": 64}], "name": "Motivaci\u00f3n Total", "release_date": "2022-03-01", "release_date_precision": "day", "total_tracks": 40, "type": "album", "uri": "spotify:album:4WDRDad9ws4RcFYn2dCZsL"}, "artists": [{"external_urls": {"spotify": "https://open.spotify.com/artist/1wZtkThiXbVNtj6hee6dz9"}, "href": "https://api.spotify.com/v1/artists/1wZtkThiXbVNtj6hee6dz9", "id": "1wZtkThiXbVNtj6hee6dz9", "name": "Wisin & Yandel", "type": "artist", "uri": "spotify:artist:1wZtkThiXbVNtj6hee6dz9"}], "disc_number": 1, "duration_ms": 234546, "explicit": false, "external_ids": {"isrc": "USUM70614082"}, "external_urls": {"spotify": "https://open.spotify.com/track/4vGtWwGFW5ORcC2w5OUIBe"}, "href": "https://api.spotify.com/v1/tracks/4vGtWwGFW5ORcC2w5OUIBe", "id": "4vGtWwGFW5ORcC2w5OUIBe", "is_local": false, "is_playable": true, "name": "Pegao", "popularity": 0, "preview_url": null, "track_number": 29, "type": "track", "uri": "spotify:track:4vGtWwGFW5ORcC2w5OUIBe"}, {"album": {"album_type": "album", "artists": [{"external_urls": {"spotify": "https://open.spotify.com/artist/0LyfQWJT6nXafLPZqxe9Of"}, "href": "https://api.spotify.com/v1/artists/0LyfQWJT6nXafLPZqxe9Of", "id": "0LyfQWJT6nXafLPZqxe9Of", "name": "Various Artists", "type": "artist", "uri": "spotify:artist:0LyfQWJT6nXafLPZqxe9Of"}], "external_urls": {"spotify": "https://open.spotify.com/album/1Zyo7gYEDbMwex8WSD461X"}, "href": "https://api.spotify.com/v1/albums/1Zyo7gYEDbMwex8WSD461X", "id": "1Zyo7gYEDbMwex8WSD461X", "images": [{"height": 640, "url": "https://i.scdn.co/image/ab67616d0000b2730cb5146e939df47d1de1f4f0", "width": 640}, {"height": 300, "url": "https://i.scdn.co/image/ab67616d00001e020cb5146e939df47d1de1f4f0", "width": 300}, {"height": 64, "url": "https://i.scdn.co/image/ab67616d000048510cb5146e939df47d1de1f4f0", "width": 64}], "name": "Tardecita Retro", "release_date": "2022-03-04", "release_date_precision": "day", "total_tracks": 40, "type": "album", "uri": "spotify:album:1Zyo7gYEDbMwex8WSD461X"}, "artists": [{"external_urls": {"spotify": "https://open.spotify.com/artist/1wZtkThiXbVNtj6hee6dz9"}, "href": "https://api.spotify.com/v1/artists/1wZtkThiXbVNtj6hee6dz9", "id": "1wZtkThiXbVNtj6hee6dz9", "name": "Wisin & Yandel", "type": "artist", "uri": "spotify:artist:1wZtkThiXbVNtj6hee6dz9"}], "disc_number": 1, "duration_ms": 259066, "explicit": false, "external_ids": {"isrc": "USUM70998449"}, "external_urls": {"spotify": "https://open.spotify.com/track/5GLRtuCxarRaniX3K9yI8Z"}, "href": "https://api.spotify.com/v1/tracks/5GLRtuCxarRaniX3K9yI8Z", "id": "5GLRtuCxarRaniX3K9yI8Z", "is_local": false, "is_playable": true, "name": "Te Siento", "popularity": 0, "preview_url": null, "track_number": 32, "type": "track", "uri": "spotify:track:5GLRtuCxarRaniX3K9yI8Z"}, {"album": {"album_type": "album", "artists": [{"external_urls": {"spotify": "https://open.spotify.com/artist/0LyfQWJT6nXafLPZqxe9Of"}, "href": "https://api.spotify.com/v1/artists/0LyfQWJT6nXafLPZqxe9Of", "id": "0LyfQWJT6nXafLPZqxe9Of", "name": "Various Artists", "type": "artist", "uri": "spotify:artist:0LyfQWJT6nXafLPZqxe9Of"}], "external_urls": {"spotify": "https://open.spotify.com/album/3xDvTQooFakwwGfUoqkgSP"}, "href": "https://api.spotify.com/v1/albums/3xDvTQooFakwwGfUoqkgSP", "id": "3xDvTQooFakwwGfUoqkgSP", "images": [{"height": 640, "url": "https://i.scdn.co/image/ab67616d0000b27373b8ae7590f1959ad47d7590", "width": 640}, {"height": 300, "url": "https://i.scdn.co/image/ab67616d00001e0273b8ae7590f1959ad47d7590", "width": 300}, {"height": 64, "url": "https://i.scdn.co/image/ab67616d0000485173b8ae7590f1959ad47d7590", "width": 64}], "name": "Hitazos Veraniegos", "release_date": "2022-02-22", "release_date_precision": "day", "total_tracks": 36, "type": "album", "uri": "spotify:album:3xDvTQooFakwwGfUoqkgSP"}, "artists": [{"external_urls": {"spotify": "https://open.spotify.com/artist/1wZtkThiXbVNtj6hee6dz9"}, "href": "https://api.spotify.com/v1/artists/1wZtkThiXbVNtj6hee6dz9", "id": "1wZtkThiXbVNtj6hee6dz9", "name": "Wisin & Yandel", "type": "artist", "uri": "spotify:artist:1wZtkThiXbVNtj6hee6dz9"}], "disc_number": 1, "duration_ms": 234546, "explicit": false, "external_ids": {"isrc": "USUM70614082"}, "external_urls": {"spotify": "https://open.spotify.com/track/3GoGpqMQqPoMObkHznPdPO"}, "href": "https://api.spotify.com/v1/tracks/3GoGpqMQqPoMObkHznPdPO", "id": "3GoGpqMQqPoMObkHznPdPO", "is_local": false, "is_playable": true, "name": "Pegao", "popularity": 0, "preview_url": null, "track_number": 20, "type": "track", "uri": "spotify:track:3GoGpqMQqPoMObkHznPdPO"}, {"album": {"album_type": "album", "artists": [{"external_urls": {"spotify": "https://open.spotify.com/artist/0LyfQWJT6nXafLPZqxe9Of"}, "href": "https://api.spotify.com/v1/artists/0LyfQWJT6nXafLPZqxe9Of", "id": "0LyfQWJT6nXafLPZqxe9Of", "name": "Various Artists", "type": "artist", "uri": "spotify:artist:0LyfQWJT6nXafLPZqxe9Of"}], "external_urls": {"spotify": "https://open.spotify.com/album/42aP7bFICTsYdn5mvqL8Yy"}, "href": "https://api.spotify.com/v1/albums/42aP7bFICTsYdn5mvqL8Yy", "id": "42aP7bFICTsYdn5mvqL8Yy", "images": [{"height": 640, "url": "https://i.scdn.co/image/ab67616d0000b2736fe906ffbbffff084f445fc4", "width": 640}, {"height": 300, "url": "https://i.scdn.co/image/ab67616d00001e026fe906ffbbffff084f445fc4", "width": 300}, {"height": 64, "url": "https://i.scdn.co/image/ab67616d000048516fe906ffbbffff084f445fc4", "width": 64}], "name": "Posada De Perreo Vol. 4", "release_date": "2022-02-28", "release_date_precision": "day", "total_tracks": 24, "type": "album", "uri": "spotify:album:42aP7bFICTsYdn5mvqL8Yy"}, "artists": [{"external_urls": {"spotify": "https://open.spotify.com/artist/1wZtkThiXbVNtj6hee6dz9"}, "href": "https://api.spotify.com/v1/artists/1wZtkThiXbVNtj6hee6dz9", "id": "1wZtkThiXbVNtj6hee6dz9", "name": "Wisin & Yandel", "type": "artist", "uri": "spotify:artist:1wZtkThiXbVNtj6hee6dz9"}], "disc_number": 1, "duration_ms": 211920, "explicit": false, "external_ids": {"isrc": "USUM70754239"}, "external_urls": {"spotify": "https://open.spotify.com/track/06COojFHKtz36NaGgl2CfK"}, "href": "https://api.spotify.com/v1/tracks/06COojFHKtz36NaGgl2CfK", "id": "06COojFHKtz36NaGgl2CfK", "is_local": false, "is_playable": true, "name": "Sexy Movimiento", "popularity": 0, "preview_url": null, "track_number": 19, "type": "track", "uri": "spotify:track:06COojFHKtz36NaGgl2CfK"}, {"album": {"album_type": "album", "artists": [{"external_urls": {"spotify": "https://open.spotify.com/artist/0LyfQWJT6nXafLPZqxe9Of"}, "href": "https://api.spotify.com/v1/artists/0LyfQWJT6nXafLPZqxe9Of", "id": "0LyfQWJT6nXafLPZqxe9Of", "name": "Various Artists", "type": "artist", "uri": "spotify:artist:0LyfQWJT6nXafLPZqxe9Of"}], "external_urls": {"spotify": "https://open.spotify.com/album/3SfVNctvNNqRiwzZz3Ipz9"}, "href": "https://api.spotify.com/v1/albums/3SfVNctvNNqRiwzZz3Ipz9", "id": "3SfVNctvNNqRiwzZz3Ipz9", "images": [{"height": 640, "url": "https://i.scdn.co/image/ab67616d0000b273b7e452b8fca0bb24c35f6299", "width": 640}, {"height": 300, "url": "https://i.scdn.co/image/ab67616d00001e02b7e452b8fca0bb24c35f6299", "width": 300}, {"height": 64, "url": "https://i.scdn.co/image/ab67616d00004851b7e452b8fca0bb24c35f6299", "width": 64}], "name": "Nochecita Urbana", "release_date": "2022-03-01", "release_date_precision": "day", "total_tracks": 30, "type": "album", "uri": "spotify:album:3SfVNctvNNqRiwzZz3Ipz9"}, "artists": [{"external_urls": {"spotify": "https://open.spotify.com/artist/1wZtkThiXbVNtj6hee6dz9"}, "href": "https://api.spotify.com/v1/artists/1wZtkThiXbVNtj6hee6dz9", "id": "1wZtkThiXbVNtj6hee6dz9", "name": "Wisin & Yandel", "type": "artist", "uri": "spotify:artist:1wZtkThiXbVNtj6hee6dz9"}], "disc_number": 1, "duration_ms": 264773, "explicit": false, "external_ids": {"isrc": "USUM70963612"}, "external_urls": {"spotify": "https://open.spotify.com/track/4CUaGuQMNaluFjj9DLDEiG"}, "href": "https://api.spotify.com/v1/tracks/4CUaGuQMNaluFjj9DLDEiG", "id": "4CUaGuQMNaluFjj9DLDEiG", "is_local": false, "is_playable": true, "name": "Besos Mojados", "popularity": 0, "preview_url": null, "track_number": 20, "type": "track", "uri": "spotify:track:4CUaGuQMNaluFjj9DLDEiG"}, {"album": {"album_type": "album", "artists": [{"external_urls": {"spotify": "https://open.spotify.com/artist/0LyfQWJT6nXafLPZqxe9Of"}, "href": "https://api.spotify.com/v1/artists/0LyfQWJT6nXafLPZqxe9Of", "id": "0LyfQWJT6nXafLPZqxe9Of", "name": "Various Artists", "type": "artist", "uri": "spotify:artist:0LyfQWJT6nXafLPZqxe9Of"}], "external_urls": {"spotify": "https://open.spotify.com/album/1prkRPDozEuVUupgCMucw1"}, "href": "https://api.spotify.com/v1/albums/1prkRPDozEuVUupgCMucw1", "id": "1prkRPDozEuVUupgCMucw1", "images": [{"height": 640, "url": "https://i.scdn.co/image/ab67616d0000b273a4f03355009ebdab31641340", "width": 640}, {"height": 300, "url": "https://i.scdn.co/image/ab67616d00001e02a4f03355009ebdab31641340", "width": 300}, {"height": 64, "url": "https://i.scdn.co/image/ab67616d00004851a4f03355009ebdab31641340", "width": 64}], "name": "Ponle Replay", "release_date": "2022-02-18", "release_date_precision": "day", "total_tracks": 36, "type": "album", "uri": "spotify:album:1prkRPDozEuVUupgCMucw1"}, "artists": [{"external_urls": {"spotify": "https://open.spotify.com/artist/1wZtkThiXbVNtj6hee6dz9"}, "href": "https://api.spotify.com/v1/artists/1wZtkThiXbVNtj6hee6dz9", "id": "1wZtkThiXbVNtj6hee6dz9", "name": "Wisin & Yandel", "type": "artist", "uri": "spotify:artist:1wZtkThiXbVNtj6hee6dz9"}], "disc_number": 1, "duration_ms": 246853, "explicit": false, "external_ids": {"isrc": "USUM71029769"}, "external_urls": {"spotify": "https://open.spotify.com/track/62DQ3mgkrRB3MlhO5y4lSm"}, "href": "https://api.spotify.com/v1/tracks/62DQ3mgkrRB3MlhO5y4lSm", "id": "62DQ3mgkrRB3MlhO5y4lSm", "is_local": false, "is_playable": true, "name": "Tu Olor", "popularity": 0, "preview_url": null, "track_number": 13, "type": "track", "uri": "spotify:track:62DQ3mgkrRB3MlhO5y4lSm"}, {"album": {"album_type": "compilation", "artists": [{"external_urls": {"spotify": "https://open.spotify.com/artist/0LyfQWJT6nXafLPZqxe9Of"}, "href": "https://api.spotify.com/v1/artists/0LyfQWJT6nXafLPZqxe9Of", "id": "0LyfQWJT6nXafLPZqxe9Of", "name": "Various Artists", "type": "artist", "uri": "spotify:artist:0LyfQWJT6nXafLPZqxe9Of"}], "external_urls": {"spotify": "https://open.spotify.com/album/34tnCEyAxxYzME7uWNaIf9"}, "href": "https://api.spotify.com/v1/albums/34tnCEyAxxYzME7uWNaIf9", "id": "34tnCEyAxxYzME7uWNaIf9", "images": [{"height": 640, "url": "https://i.scdn.co/image/ab67616d0000b273da6c3f99da9df338af96a0ed", "width": 640}, {"height": 300, "url": "https://i.scdn.co/image/ab67616d00001e02da6c3f99da9df338af96a0ed", "width": 300}, {"height": 64, "url": "https://i.scdn.co/image/ab67616d00004851da6c3f99da9df338af96a0ed", "width": 64}], "name": "Partusa Latina", "release_date": "2022-02-28", "release_date_precision": "day", "total_tracks": 40, "type": "album", "uri": "spotify:album:34tnCEyAxxYzME7uWNaIf9"}, "artists": [{"external_urls": {"spotify": "https://open.spotify.com/artist/1wZtkThiXbVNtj6hee6dz9"}, "href": "https://api.spotify.com/v1/artists/1wZtkThiXbVNtj6hee6dz9", "id": "1wZtkThiXbVNtj6hee6dz9", "name": "Wisin & Yandel", "type": "artist", "uri": "spotify:artist:1wZtkThiXbVNtj6hee6dz9"}], "disc_number": 1, "duration_ms": 180386, "explicit": false, "external_ids": {"isrc": "USUM70963610"}, "external_urls": {"spotify": "https://open.spotify.com/track/0KWaoqpHyWDuEghi4RFa06"}, "href": "https://api.spotify.com/v1/tracks/0KWaoqpHyWDuEghi4RFa06", "id": "0KWaoqpHyWDuEghi4RFa06", "is_local": false, "is_playable": true, "name": "Abusadora", "popularity": 0, "preview_url": null, "track_number": 3, "type": "track", "uri": "spotify:track:0KWaoqpHyWDuEghi4RFa06"}, {"album": {"album_type": "album", "artists": [{"external_urls": {"spotify": "https://open.spotify.com/artist/0LyfQWJT6nXafLPZqxe9Of"}, "href": "https://api.spotify.com/v1/artists/0LyfQWJT6nXafLPZqxe9Of", "id": "0LyfQWJT6nXafLPZqxe9Of", "name": "Various Artists", "type": "artist", "uri": "spotify:artist:0LyfQWJT6nXafLPZqxe9Of"}], "external_urls": {"spotify": "https://open.spotify.com/album/4PpM4aVrxIAHvj2DBpBOkv"}, "href": "https://api.spotify.com/v1/albums/4PpM4aVrxIAHvj2DBpBOkv", "id": "4PpM4aVrxIAHvj2DBpBOkv", "images": [{"height": 640, "url": "https://i.scdn.co/image/ab67616d0000b273d309e1f09933b70a2cca4f3c", "width": 640}, {"height": 300, "url": "https://i.scdn.co/image/ab67616d00001e02d309e1f09933b70a2cca4f3c", "width": 300}, {"height": 64, "url": "https://i.scdn.co/image/ab67616d00004851d309e1f09933b70a2cca4f3c", "width": 64}], "name": "Modo Veranito", "release_date": "2022-02-28", "release_date_precision": "day", "total_tracks": 40, "type": "album", "uri": "spotify:album:4PpM4aVrxIAHvj2DBpBOkv"}, "artists": [{"external_urls": {"spotify": "https://open.spotify.com/artist/1wZtkThiXbVNtj6hee6dz9"}, "href": "https://api.spotify.com/v1/artists/1wZtkThiXbVNtj6hee6dz9", "id": "1wZtkThiXbVNtj6hee6dz9", "name": "Wisin & Yandel", "type": "artist", "uri": "spotify:artist:1wZtkThiXbVNtj6hee6dz9"}], "disc_number": 1, "duration_ms": 227280, "explicit": false, "external_ids": {"isrc": "USUM70602421"}, "external_urls": {"spotify": "https://open.spotify.com/track/67GeUCGfYrCZ5iab8ImLLW"}, "href": "https://api.spotify.com/v1/tracks/67GeUCGfYrCZ5iab8ImLLW", "id": "67GeUCGfYrCZ5iab8ImLLW", "is_local": false, "is_playable": true, "name": "Pam Pam", "popularity": 0, "preview_url": null, "track_number": 16, "type": "track", "uri": "spotify:track:67GeUCGfYrCZ5iab8ImLLW"}, {"album": {"album_type": "album", "artists": [{"external_urls": {"spotify": "https://open.spotify.com/artist/0LyfQWJT6nXafLPZqxe9Of"}, "href": "https://api.spotify.com/v1/artists/0LyfQWJT6nXafLPZqxe9Of", "id": "0LyfQWJT6nXafLPZqxe9Of", "name": "Various Artists", "type": "artist", "uri": "spotify:artist:0LyfQWJT6nXafLPZqxe9Of"}], "external_urls": {"spotify": "https://open.spotify.com/album/4TMTsa4gwGeOSJbKmtyqGC"}, "href": "https://api.spotify.com/v1/albums/4TMTsa4gwGeOSJbKmtyqGC", "id": "4TMTsa4gwGeOSJbKmtyqGC", "images": [{"height": 640, "url": "https://i.scdn.co/image/ab67616d0000b2737ce32082cdb785b77fe6a9b5", "width": 640}, {"height": 300, "url": "https://i.scdn.co/image/ab67616d00001e027ce32082cdb785b77fe6a9b5", "width": 300}, {"height": 64, "url": "https://i.scdn.co/image/ab67616d000048517ce32082cdb785b77fe6a9b5", "width": 64}], "name": "Reguet\u00f3n Inolvidable", "release_date": "2022-02-28", "release_date_precision": "day", "total_tracks": 40, "type": "album", "uri": "spotify:album:4TMTsa4gwGeOSJbKmtyqGC"}, "artists": [{"external_urls": {"spotify": "https://open.spotify.com/artist/1wZtkThiXbVNtj6hee6dz9"}, "href": "https://api.spotify.com/v1/artists/1wZtkThiXbVNtj6hee6dz9", "id": "1wZtkThiXbVNtj6hee6dz9", "name": "Wisin & Yandel", "type": "artist", "uri": "spotify:artist:1wZtkThiXbVNtj6hee6dz9"}], "disc_number": 1, "duration_ms": 207186, "explicit": false, "external_ids": {"isrc": "USUM70756397"}, "external_urls": {"spotify": "https://open.spotify.com/track/1j5iVqjvpnw72Nr7MK4opb"}, "href": "https://api.spotify.com/v1/tracks/1j5iVqjvpnw72Nr7MK4opb", "id": "1j5iVqjvpnw72Nr7MK4opb", "is_local": false, "is_playable": true, "name": "Ahora Es", "popularity": 0, "preview_url": null, "track_number": 20, "type": "track", "uri": "spotify:track:1j5iVqjvpnw72Nr7MK4opb"}, {"album": {"album_type": "album", "artists": [{"external_urls": {"spotify": "https://open.spotify.com/artist/0LyfQWJT6nXafLPZqxe9Of"}, "href": "https://api.spotify.com/v1/artists/0LyfQWJT6nXafLPZqxe9Of", "id": "0LyfQWJT6nXafLPZqxe9Of", "name": "Various Artists", "type": "artist", "uri": "spotify:artist:0LyfQWJT6nXafLPZqxe9Of"}], "external_urls": {"spotify": "https://open.spotify.com/album/4PpM4aVrxIAHvj2DBpBOkv"}, "href": "https://api.spotify.com/v1/albums/4PpM4aVrxIAHvj2DBpBOkv", "id": "4PpM4aVrxIAHvj2DBpBOkv", "images": [{"height": 640, "url": "https://i.scdn.co/image/ab67616d0000b273d309e1f09933b70a2cca4f3c", "width": 640}, {"height": 300, "url": "https://i.scdn.co/image/ab67616d00001e02d309e1f09933b70a2cca4f3c", "width": 300}, {"height": 64, "url": "https://i.scdn.co/image/ab67616d00004851d309e1f09933b70a2cca4f3c", "width": 64}], "name": "Modo Veranito", "release_date": "2022-02-28", "release_date_precision": "day", "total_tracks": 40, "type": "album", "uri": "spotify:album:4PpM4aVrxIAHvj2DBpBOkv"}, "artists": [{"external_urls": {"spotify": "https://open.spotify.com/artist/1wZtkThiXbVNtj6hee6dz9"}, "href": "https://api.spotify.com/v1/artists/1wZtkThiXbVNtj6hee6dz9", "id": "1wZtkThiXbVNtj6hee6dz9", "name": "Wisin & Yandel", "type": "artist", "uri": "spotify:artist:1wZtkThiXbVNtj6hee6dz9"}], "disc_number": 1, "duration_ms": 246853, "explicit": false, "external_ids": {"isrc": "USUM71029769"}, "external_urls": {"spotify": "https://open.spotify.com/track/6edfZ7VojvHZZv6Sa4i2b7"}, "href": "https://api.spotify.com/v1/tracks/6edfZ7VojvHZZv6Sa4i2b7", "id": "6edfZ7VojvHZZv6Sa4i2b7", "is_local": false, "is_playable": true, "name": "Tu Olor", "popularity": 0, "preview_url": null, "track_number": 25, "type": "track", "uri": "spotify:track:6edfZ7VojvHZZv6Sa4i2b7"}, {"album": {"album_type": "album", "artists": [{"external_urls": {"spotify": "https://open.spotify.com/artist/0LyfQWJT6nXafLPZqxe9Of"}, "href": "https://api.spotify.com/v1/artists/0LyfQWJT6nXafLPZqxe9Of", "id": "0LyfQWJT6nXafLPZqxe9Of", "name": "Various Artists", "type": "artist", "uri": "spotify:artist:0LyfQWJT6nXafLPZqxe9Of"}], "external_urls": {"spotify": "https://open.spotify.com/album/2FX8wjvsrdHnX18Uo3cGZr"}, "href": "https://api.spotify.com/v1/albums/2FX8wjvsrdHnX18Uo3cGZr", "id": "2FX8wjvsrdHnX18Uo3cGZr", "images": [{"height": 640, "url": "https://i.scdn.co/image/ab67616d0000b27367bd52effcba814f20417cc1", "width": 640}, {"height": 300, "url": "https://i.scdn.co/image/ab67616d00001e0267bd52effcba814f20417cc1", "width": 300}, {"height": 64, "url": "https://i.scdn.co/image/ab67616d0000485167bd52effcba814f20417cc1", "width": 64}], "name": "Temones Esenciales", "release_date": "2022-03-04", "release_date_precision": "day", "total_tracks": 35, "type": "album", "uri": "spotify:album:2FX8wjvsrdHnX18Uo3cGZr"}, "artists": [{"external_urls": {"spotify": "https://open.spotify.com/artist/1wZtkThiXbVNtj6hee6dz9"}, "href": "https://api.spotify.com/v1/artists/1wZtkThiXbVNtj6hee6dz9", "id": "1wZtkThiXbVNtj6hee6dz9", "name": "Wisin & Yandel", "type": "artist", "uri": "spotify:artist:1wZtkThiXbVNtj6hee6dz9"}], "disc_number": 1, "duration_ms": 264773, "explicit": false, "external_ids": {"isrc": "USUM70963612"}, "external_urls": {"spotify": "https://open.spotify.com/track/2dqESTfeaBSm6A0cFsVx6Y"}, "href": "https://api.spotify.com/v1/tracks/2dqESTfeaBSm6A0cFsVx6Y", "id": "2dqESTfeaBSm6A0cFsVx6Y", "is_local": false, "is_playable": true, "name": "Besos Mojados", "popularity": 0, "preview_url": null, "track_number": 13, "type": "track", "uri": "spotify:track:2dqESTfeaBSm6A0cFsVx6Y"}, {"album": {"album_type": "compilation", "artists": [{"external_urls": {"spotify": "https://open.spotify.com/artist/0LyfQWJT6nXafLPZqxe9Of"}, "href": "https://api.spotify.com/v1/artists/0LyfQWJT6nXafLPZqxe9Of", "id": "0LyfQWJT6nXafLPZqxe9Of", "name": "Various Artists", "type": "artist", "uri": "spotify:artist:0LyfQWJT6nXafLPZqxe9Of"}], "external_urls": {"spotify": "https://open.spotify.com/album/2Lq78nM1NuI27xUqSzl68j"}, "href": "https://api.spotify.com/v1/albums/2Lq78nM1NuI27xUqSzl68j", "id": "2Lq78nM1NuI27xUqSzl68j", "images": [{"height": 640, "url": "https://i.scdn.co/image/ab67616d0000b2737808d62b9e4f1c5dce15f307", "width": 640}, {"height": 300, "url": "https://i.scdn.co/image/ab67616d00001e027808d62b9e4f1c5dce15f307", "width": 300}, {"height": 64, "url": "https://i.scdn.co/image/ab67616d000048517808d62b9e4f1c5dce15f307", "width": 64}], "name": "Bailoteo Gal\u00e1ctico", "release_date": "2022-02-23", "release_date_precision": "day", "total_tracks": 30, "type": "album", "uri": "spotify:album:2Lq78nM1NuI27xUqSzl68j"}, "artists": [{"external_urls": {"spotify": "https://open.spotify.com/artist/1wZtkThiXbVNtj6hee6dz9"}, "href": "https://api.spotify.com/v1/artists/1wZtkThiXbVNtj6hee6dz9", "id": "1wZtkThiXbVNtj6hee6dz9", "name": "Wisin & Yandel", "type": "artist", "uri": "spotify:artist:1wZtkThiXbVNtj6hee6dz9"}, {"external_urls": {"spotify": "https://open.spotify.com/artist/33ScadVnbm2X8kkUqOkC6Z"}, "href": "https://api.spotify.com/v1/artists/33ScadVnbm2X8kkUqOkC6Z", "id": "33ScadVnbm2X8kkUqOkC6Z", "name": "Don Omar", "type": "artist", "uri": "spotify:artist:33ScadVnbm2X8kkUqOkC6Z"}], "disc_number": 1, "duration_ms": 223266, "explicit": false, "external_ids": {"isrc": "USUM70614167"}, "external_urls": {"spotify": "https://open.spotify.com/track/6RgeaBFVSFfDdkEBP6VpwS"}, "href": "https://api.spotify.com/v1/tracks/6RgeaBFVSFfDdkEBP6VpwS", "id": "6RgeaBFVSFfDdkEBP6VpwS", "is_local": false, "is_playable": true, "name": "Nadie Como Tu", "popularity": 2, "preview_url": null, "track_number": 27, "type": "track", "uri": "spotify:track:6RgeaBFVSFfDdkEBP6VpwS"}, {"album": {"album_type": "album", "artists": [{"external_urls": {"spotify": "https://open.spotify.com/artist/0LyfQWJT6nXafLPZqxe9Of"}, "href": "https://api.spotify.com/v1/artists/0LyfQWJT6nXafLPZqxe9Of", "id": "0LyfQWJT6nXafLPZqxe9Of", "name": "Various Artists", "type": "artist", "uri": "spotify:artist:0LyfQWJT6nXafLPZqxe9Of"}], "external_urls": {"spotify": "https://open.spotify.com/album/0p1XEYtBpP3vIGKQAzGNbi"}, "href": "https://api.spotify.com/v1/albums/0p1XEYtBpP3vIGKQAzGNbi", "id": "0p1XEYtBpP3vIGKQAzGNbi", "images": [{"height": 640, "url": "https://i.scdn.co/image/ab67616d0000b273a1c2a037ecdf76153666d83c", "width": 640}, {"height": 300, "url": "https://i.scdn.co/image/ab67616d00001e02a1c2a037ecdf76153666d83c", "width": 300}, {"height": 64, "url": "https://i.scdn.co/image/ab67616d00004851a1c2a037ecdf76153666d83c", "width": 64}], "name": "Radar Fiestero", "release_date": "2022-03-02", "release_date_precision": "day", "total_tracks": 40, "type": "album", "uri": "spotify:album:0p1XEYtBpP3vIGKQAzGNbi"}, "artists": [{"external_urls": {"spotify": "https://open.spotify.com/artist/1wZtkThiXbVNtj6hee6dz9"}, "href": "https://api.spotify.com/v1/artists/1wZtkThiXbVNtj6hee6dz9", "id": "1wZtkThiXbVNtj6hee6dz9", "name": "Wisin & Yandel", "type": "artist", "uri": "spotify:artist:1wZtkThiXbVNtj6hee6dz9"}], "disc_number": 1, "duration_ms": 259066, "explicit": false, "external_ids": {"isrc": "USUM70998449"}, "external_urls": {"spotify": "https://open.spotify.com/track/0Uy2Tie1Elb87UIwM3kheq"}, "href": "https://api.spotify.com/v1/tracks/0Uy2Tie1Elb87UIwM3kheq", "id": "0Uy2Tie1Elb87UIwM3kheq", "is_local": false, "is_playable": true, "name": "Te Siento", "popularity": 0, "preview_url": null, "track_number": 30, "type": "track", "uri": "spotify:track:0Uy2Tie1Elb87UIwM3kheq"}, {"album": {"album_type": "album", "artists": [{"external_urls": {"spotify": "https://open.spotify.com/artist/0LyfQWJT6nXafLPZqxe9Of"}, "href": "https://api.spotify.com/v1/artists/0LyfQWJT6nXafLPZqxe9Of", "id": "0LyfQWJT6nXafLPZqxe9Of", "name": "Various Artists", "type": "artist", "uri": "spotify:artist:0LyfQWJT6nXafLPZqxe9Of"}], "external_urls": {"spotify": "https://open.spotify.com/album/1yetdaTDhwWYpFPU5BTbi6"}, "href": "https://api.spotify.com/v1/albums/1yetdaTDhwWYpFPU5BTbi6", "id": "1yetdaTDhwWYpFPU5BTbi6", "images": [{"height": 640, "url": "https://i.scdn.co/image/ab67616d0000b2738ad16b3a166a79c8def4ee8c", "width": 640}, {"height": 300, "url": "https://i.scdn.co/image/ab67616d00001e028ad16b3a166a79c8def4ee8c", "width": 300}, {"height": 64, "url": "https://i.scdn.co/image/ab67616d000048518ad16b3a166a79c8def4ee8c", "width": 64}], "name": "Noches Fabulosas", "release_date": "2022-03-01", "release_date_precision": "day", "total_tracks": 36, "type": "album", "uri": "spotify:album:1yetdaTDhwWYpFPU5BTbi6"}, "artists": [{"external_urls": {"spotify": "https://open.spotify.com/artist/1wZtkThiXbVNtj6hee6dz9"}, "href": "https://api.spotify.com/v1/artists/1wZtkThiXbVNtj6hee6dz9", "id": "1wZtkThiXbVNtj6hee6dz9", "name": "Wisin & Yandel", "type": "artist", "uri": "spotify:artist:1wZtkThiXbVNtj6hee6dz9"}], "disc_number": 1, "duration_ms": 264773, "explicit": false, "external_ids": {"isrc": "USUM70963612"}, "external_urls": {"spotify": "https://open.spotify.com/track/7elecmjxPeCeXi61iK8uBH"}, "href": "https://api.spotify.com/v1/tracks/7elecmjxPeCeXi61iK8uBH", "id": "7elecmjxPeCeXi61iK8uBH", "is_local": false, "is_playable": true, "name": "Besos Mojados", "popularity": 0, "preview_url": null, "track_number": 17, "type": "track", "uri": "spotify:track:7elecmjxPeCeXi61iK8uBH"}, {"album": {"album_type": "album", "artists": [{"external_urls": {"spotify": "https://open.spotify.com/artist/3A5tHz1SfngyOZM2gItYKu"}, "href": "https://api.spotify.com/v1/artists/3A5tHz1SfngyOZM2gItYKu", "id": "3A5tHz1SfngyOZM2gItYKu", "name": "Earl Sweatshirt", "type": "artist", "uri": "spotify:artist:3A5tHz1SfngyOZM2gItYKu"}], "external_urls": {"spotify": "https://open.spotify.com/album/51heTwkSfb4Z5dRIgwU2bd"}, "href": "https://api.spotify.com/v1/albums/51heTwkSfb4Z5dRIgwU2bd", "id": "51heTwkSfb4Z5dRIgwU2bd", "images": [{"height": 640, "url": "https://i.scdn.co/image/ab67616d0000b27337834cc82e604d7c124bb951", "width": 640}, {"height": 300, "url": "https://i.scdn.co/image/ab67616d00001e0237834cc82e604d7c124bb951", "width": 300}, {"height": 64, "url": "https://i.scdn.co/image/ab67616d0000485137834cc82e604d7c124bb951", "width": 64}], "name": "SICK!", "release_date": "2022-01-14", "release_date_precision": "day", "total_tracks": 10, "type": "album", "uri": "spotify:album:51heTwkSfb4Z5dRIgwU2bd"}, "artists": [{"external_urls": {"spotify": "https://open.spotify.com/artist/3A5tHz1SfngyOZM2gItYKu"}, "href": "https://api.spotify.com/v1/artists/3A5tHz1SfngyOZM2gItYKu", "id": "3A5tHz1SfngyOZM2gItYKu", "name": "Earl Sweatshirt", "type": "artist", "uri": "spotify:artist:3A5tHz1SfngyOZM2gItYKu"}], "disc_number": 1, "duration_ms": 112625, "explicit": true, "external_ids": {"isrc": "USWB12105331"}, "external_urls": {"spotify": "https://open.spotify.com/track/23Cos3STwcp1Q1BX9MSHTC"}, "href": "https://api.spotify.com/v1/tracks/23Cos3STwcp1Q1BX9MSHTC", "id": "23Cos3STwcp1Q1BX9MSHTC", "is_local": false, "is_playable": true, "name": "Titanic", "popularity": 62, "preview_url": "https://p.scdn.co/mp3-preview/e25f791077740f46b99cfee744d1cd51f13bb8de?cid=41d11c64c99f4295b22b262d02a041ff", "track_number": 9, "type": "track", "uri": "spotify:track:23Cos3STwcp1Q1BX9MSHTC"}, {"album": {"album_type": "album", "artists": [{"external_urls": {"spotify": "https://open.spotify.com/artist/5IbEL2xjRtKsunfmsahLuO"}, "href": "https://api.spotify.com/v1/artists/5IbEL2xjRtKsunfmsahLuO", "id": "5IbEL2xjRtKsunfmsahLuO", "name": "$NOT", "type": "artist", "uri": "spotify:artist:5IbEL2xjRtKsunfmsahLuO"}], "external_urls": {"spotify": "https://open.spotify.com/album/5C1X3siQg4Q3wLWorK5i0z"}, "href": "https://api.spotify.com/v1/albums/5C1X3siQg4Q3wLWorK5i0z", "id": "5C1X3siQg4Q3wLWorK5i0z", "images": [{"height": 640, "url": "https://i.scdn.co/image/ab67616d0000b273ee72c43250d377ee9a3de52e", "width": 640}, {"height": 300, "url": "https://i.scdn.co/image/ab67616d00001e02ee72c43250d377ee9a3de52e", "width": 300}, {"height": 64, "url": "https://i.scdn.co/image/ab67616d00004851ee72c43250d377ee9a3de52e", "width": 64}], "name": "Ethereal", "release_date": "2022-02-11", "release_date_precision": "day", "total_tracks": 14, "type": "album", "uri": "spotify:album:5C1X3siQg4Q3wLWorK5i0z"}, "artists": [{"external_urls": {"spotify": "https://open.spotify.com/artist/5IbEL2xjRtKsunfmsahLuO"}, "href": "https://api.spotify.com/v1/artists/5IbEL2xjRtKsunfmsahLuO", "id": "5IbEL2xjRtKsunfmsahLuO", "name": "$NOT", "type": "artist", "uri": "spotify:artist:5IbEL2xjRtKsunfmsahLuO"}], "disc_number": 1, "duration_ms": 129345, "explicit": true, "external_ids": {"isrc": "QMCE32200132"}, "external_urls": {"spotify": "https://open.spotify.com/track/1xGrdqclNv1YXyvM28iMmD"}, "href": "https://api.spotify.com/v1/tracks/1xGrdqclNv1YXyvM28iMmD", "id": "1xGrdqclNv1YXyvM28iMmD", "is_local": false, "is_playable": true, "name": "My World (Intro)", "popularity": 64, "preview_url": "https://p.scdn.co/mp3-preview/7b6a09df03787206825075c113c31e45d2f3dd8d?cid=41d11c64c99f4295b22b262d02a041ff", "track_number": 1, "type": "track", "uri": "spotify:track:1xGrdqclNv1YXyvM28iMmD"}, {"album": {"album_type": "compilation", "artists": [{"external_urls": {"spotify": "https://open.spotify.com/artist/0LyfQWJT6nXafLPZqxe9Of"}, "href": "https://api.spotify.com/v1/artists/0LyfQWJT6nXafLPZqxe9Of", "id": "0LyfQWJT6nXafLPZqxe9Of", "name": "Various Artists", "type": "artist", "uri": "spotify:artist:0LyfQWJT6nXafLPZqxe9Of"}], "external_urls": {"spotify": "https://open.spotify.com/album/6mNEJEYod7YRQcPHdDwkk9"}, "href": "https://api.spotify.com/v1/albums/6mNEJEYod7YRQcPHdDwkk9", "id": "6mNEJEYod7YRQcPHdDwkk9", "images": [{"height": 640, "url": "https://i.scdn.co/image/ab67616d0000b273fc5c8e0d11660288f7029757", "width": 640}, {"height": 300, "url": "https://i.scdn.co/image/ab67616d00001e02fc5c8e0d11660288f7029757", "width": 300}, {"height": 64, "url": "https://i.scdn.co/image/ab67616d00004851fc5c8e0d11660288f7029757", "width": 64}], "name": "Cowboys Don't Cry - Pop Up", "release_date": "2022-03-04", "release_date_precision": "day", "total_tracks": 40, "type": "album", "uri": "spotify:album:6mNEJEYod7YRQcPHdDwkk9"}, "artists": [{"external_urls": {"spotify": "https://open.spotify.com/artist/6TLwD7HPWuiOzvXEa3oCNe"}, "href": "https://api.spotify.com/v1/artists/6TLwD7HPWuiOzvXEa3oCNe", "id": "6TLwD7HPWuiOzvXEa3oCNe", "name": "Oliver Tree", "type": "artist", "uri": "spotify:artist:6TLwD7HPWuiOzvXEa3oCNe"}], "disc_number": 1, "duration_ms": 189969, "explicit": false, "external_ids": {"isrc": "USAT22107445"}, "external_urls": {"spotify": "https://open.spotify.com/track/3moTuEU49dScjvWj42CLnN"}, "href": "https://api.spotify.com/v1/tracks/3moTuEU49dScjvWj42CLnN", "id": "3moTuEU49dScjvWj42CLnN", "is_local": false, "is_playable": true, "name": "Cowboys Don\u2019t Cry", "popularity": 0, "preview_url": "https://p.scdn.co/mp3-preview/17f52c1fa9882fe9737a69b41830c1754fedc1e3?cid=41d11c64c99f4295b22b262d02a041ff", "track_number": 1, "type": "track", "uri": "spotify:track:3moTuEU49dScjvWj42CLnN"}, {"album": {"album_type": "album", "artists": [{"external_urls": {"spotify": "https://open.spotify.com/artist/0LyfQWJT6nXafLPZqxe9Of"}, "href": "https://api.spotify.com/v1/artists/0LyfQWJT6nXafLPZqxe9Of", "id": "0LyfQWJT6nXafLPZqxe9Of", "name": "Various Artists", "type": "artist", "uri": "spotify:artist:0LyfQWJT6nXafLPZqxe9Of"}], "external_urls": {"spotify": "https://open.spotify.com/album/5X5RkGznWTOQdgLcQWDKpp"}, "href": "https://api.spotify.com/v1/albums/5X5RkGznWTOQdgLcQWDKpp", "id": "5X5RkGznWTOQdgLcQWDKpp", "images": [{"height": 640, "url": "https://i.scdn.co/image/ab67616d0000b273482888246c071350bfcc2396", "width": 640}, {"height": 300, "url": "https://i.scdn.co/image/ab67616d00001e02482888246c071350bfcc2396", "width": 300}, {"height": 64, "url": "https://i.scdn.co/image/ab67616d00004851482888246c071350bfcc2396", "width": 64}], "name": "Notion - Indie Bangers", "release_date": "2022-03-04", "release_date_precision": "day", "total_tracks": 25, "type": "album", "uri": "spotify:album:5X5RkGznWTOQdgLcQWDKpp"}, "artists": [{"external_urls": {"spotify": "https://open.spotify.com/artist/6TLwD7HPWuiOzvXEa3oCNe"}, "href": "https://api.spotify.com/v1/artists/6TLwD7HPWuiOzvXEa3oCNe", "id": "6TLwD7HPWuiOzvXEa3oCNe", "name": "Oliver Tree", "type": "artist", "uri": "spotify:artist:6TLwD7HPWuiOzvXEa3oCNe"}], "disc_number": 1, "duration_ms": 189969, "explicit": false, "external_ids": {"isrc": "USAT22107445"}, "external_urls": {"spotify": "https://open.spotify.com/track/17XNG6rOmGSStDmrJELHZ9"}, "href": "https://api.spotify.com/v1/tracks/17XNG6rOmGSStDmrJELHZ9", "id": "17XNG6rOmGSStDmrJELHZ9", "is_local": false, "is_playable": true, "name": "Cowboys Don\u2019t Cry", "popularity": 0, "preview_url": "https://p.scdn.co/mp3-preview/17f52c1fa9882fe9737a69b41830c1754fedc1e3?cid=41d11c64c99f4295b22b262d02a041ff", "track_number": 15, "type": "track", "uri": "spotify:track:17XNG6rOmGSStDmrJELHZ9"}, {"album": {"album_type": "album", "artists": [{"external_urls": {"spotify": "https://open.spotify.com/artist/0LyfQWJT6nXafLPZqxe9Of"}, "href": "https://api.spotify.com/v1/artists/0LyfQWJT6nXafLPZqxe9Of", "id": "0LyfQWJT6nXafLPZqxe9Of", "name": "Various Artists", "type": "artist", "uri": "spotify:artist:0LyfQWJT6nXafLPZqxe9Of"}], "external_urls": {"spotify": "https://open.spotify.com/album/6KyQQSWrMTyJTnoDwP91uB"}, "href": "https://api.spotify.com/v1/albums/6KyQQSWrMTyJTnoDwP91uB", "id": "6KyQQSWrMTyJTnoDwP91uB", "images": [{"height": 640, "url": "https://i.scdn.co/image/ab67616d0000b273e4c7ab6378728daf17fb2a8e", "width": 640}, {"height": 300, "url": "https://i.scdn.co/image/ab67616d00001e02e4c7ab6378728daf17fb2a8e", "width": 300}, {"height": 64, "url": "https://i.scdn.co/image/ab67616d00004851e4c7ab6378728daf17fb2a8e", "width": 64}], "name": "I Look Good - Trending Now", "release_date": "2022-03-04", "release_date_precision": "day", "total_tracks": 30, "type": "album", "uri": "spotify:album:6KyQQSWrMTyJTnoDwP91uB"}, "artists": [{"external_urls": {"spotify": "https://open.spotify.com/artist/6TLwD7HPWuiOzvXEa3oCNe"}, "href": "https://api.spotify.com/v1/artists/6TLwD7HPWuiOzvXEa3oCNe", "id": "6TLwD7HPWuiOzvXEa3oCNe", "name": "Oliver Tree", "type": "artist", "uri": "spotify:artist:6TLwD7HPWuiOzvXEa3oCNe"}], "disc_number": 1, "duration_ms": 189969, "explicit": false, "external_ids": {"isrc": "USAT22107445"}, "external_urls": {"spotify": "https://open.spotify.com/track/4btzBLO2TjHPft56e5IQsy"}, "href": "https://api.spotify.com/v1/tracks/4btzBLO2TjHPft56e5IQsy", "id": "4btzBLO2TjHPft56e5IQsy", "is_local": false, "is_playable": true, "name": "Cowboys Don\u2019t Cry", "popularity": 0, "preview_url": "https://p.scdn.co/mp3-preview/17f52c1fa9882fe9737a69b41830c1754fedc1e3?cid=41d11c64c99f4295b22b262d02a041ff", "track_number": 8, "type": "track", "uri": "spotify:track:4btzBLO2TjHPft56e5IQsy"}, {"album": {"album_type": "compilation", "artists": [{"external_urls": {"spotify": "https://open.spotify.com/artist/0LyfQWJT6nXafLPZqxe9Of"}, "href": "https://api.spotify.com/v1/artists/0LyfQWJT6nXafLPZqxe9Of", "id": "0LyfQWJT6nXafLPZqxe9Of", "name": "Various Artists", "type": "artist", "uri": "spotify:artist:0LyfQWJT6nXafLPZqxe9Of"}], "external_urls": {"spotify": "https://open.spotify.com/album/1sL1IBeMJvgiwsZUJNcuZ3"}, "href": "https://api.spotify.com/v1/albums/1sL1IBeMJvgiwsZUJNcuZ3", "id": "1sL1IBeMJvgiwsZUJNcuZ3", "images": [{"height": 640, "url": "https://i.scdn.co/image/ab67616d0000b2735dcf0bf246939a546ae1b83a", "width": 640}, {"height": 300, "url": "https://i.scdn.co/image/ab67616d00001e025dcf0bf246939a546ae1b83a", "width": 300}, {"height": 64, "url": "https://i.scdn.co/image/ab67616d000048515dcf0bf246939a546ae1b83a", "width": 64}], "name": "Massive 20's Hits", "release_date": "2022-03-04", "release_date_precision": "day", "total_tracks": 30, "type": "album", "uri": "spotify:album:1sL1IBeMJvgiwsZUJNcuZ3"}, "artists": [{"external_urls": {"spotify": "https://open.spotify.com/artist/6TLwD7HPWuiOzvXEa3oCNe"}, "href": "https://api.spotify.com/v1/artists/6TLwD7HPWuiOzvXEa3oCNe", "id": "6TLwD7HPWuiOzvXEa3oCNe", "name": "Oliver Tree", "type": "artist", "uri": "spotify:artist:6TLwD7HPWuiOzvXEa3oCNe"}], "disc_number": 1, "duration_ms": 161803, "explicit": false, "external_ids": {"isrc": "USAT22007153"}, "external_urls": {"spotify": "https://open.spotify.com/track/3ens7n9BZPEnlSk6vKND3z"}, "href": "https://api.spotify.com/v1/tracks/3ens7n9BZPEnlSk6vKND3z", "id": "3ens7n9BZPEnlSk6vKND3z", "is_local": false, "is_playable": true, "name": "Life Goes On", "popularity": 0, "preview_url": "https://p.scdn.co/mp3-preview/8263e9905c7744096b876feb779190c14eee550c?cid=41d11c64c99f4295b22b262d02a041ff", "track_number": 24, "type": "track", "uri": "spotify:track:3ens7n9BZPEnlSk6vKND3z"}, {"album": {"album_type": "album", "artists": [{"external_urls": {"spotify": "https://open.spotify.com/artist/0LyfQWJT6nXafLPZqxe9Of"}, "href": "https://api.spotify.com/v1/artists/0LyfQWJT6nXafLPZqxe9Of", "id": "0LyfQWJT6nXafLPZqxe9Of", "name": "Various Artists", "type": "artist", "uri": "spotify:artist:0LyfQWJT6nXafLPZqxe9Of"}], "external_urls": {"spotify": "https://open.spotify.com/album/3fuUu5AQ7zBchcWoFTyuAV"}, "href": "https://api.spotify.com/v1/albums/3fuUu5AQ7zBchcWoFTyuAV", "id": "3fuUu5AQ7zBchcWoFTyuAV", "images": [{"height": 640, "url": "https://i.scdn.co/image/ab67616d0000b273acf288534c3d363f3bf813cc", "width": 640}, {"height": 300, "url": "https://i.scdn.co/image/ab67616d00001e02acf288534c3d363f3bf813cc", "width": 300}, {"height": 64, "url": "https://i.scdn.co/image/ab67616d00004851acf288534c3d363f3bf813cc", "width": 64}], "name": "Rather Be - Uplifting Pop Songs", "release_date": "2022-03-04", "release_date_precision": "day", "total_tracks": 30, "type": "album", "uri": "spotify:album:3fuUu5AQ7zBchcWoFTyuAV"}, "artists": [{"external_urls": {"spotify": "https://open.spotify.com/artist/6TLwD7HPWuiOzvXEa3oCNe"}, "href": "https://api.spotify.com/v1/artists/6TLwD7HPWuiOzvXEa3oCNe", "id": "6TLwD7HPWuiOzvXEa3oCNe", "name": "Oliver Tree", "type": "artist", "uri": "spotify:artist:6TLwD7HPWuiOzvXEa3oCNe"}], "disc_number": 1, "duration_ms": 161803, "explicit": false, "external_ids": {"isrc": "USAT22007153"}, "external_urls": {"spotify": "https://open.spotify.com/track/5S7cJqMNd0RyYNiIQx45Bf"}, "href": "https://api.spotify.com/v1/tracks/5S7cJqMNd0RyYNiIQx45Bf", "id": "5S7cJqMNd0RyYNiIQx45Bf", "is_local": false, "is_playable": true, "name": "Life Goes On", "popularity": 0, "preview_url": "https://p.scdn.co/mp3-preview/8263e9905c7744096b876feb779190c14eee550c?cid=41d11c64c99f4295b22b262d02a041ff", "track_number": 26, "type": "track", "uri": "spotify:track:5S7cJqMNd0RyYNiIQx45Bf"}, {"album": {"album_type": "album", "artists": [{"external_urls": {"spotify": "https://open.spotify.com/artist/0LyfQWJT6nXafLPZqxe9Of"}, "href": "https://api.spotify.com/v1/artists/0LyfQWJT6nXafLPZqxe9Of", "id": "0LyfQWJT6nXafLPZqxe9Of", "name": "Various Artists", "type": "artist", "uri": "spotify:artist:0LyfQWJT6nXafLPZqxe9Of"}], "external_urls": {"spotify": "https://open.spotify.com/album/7nR0FDiIhGlZ0vJGWT0xib"}, "href": "https://api.spotify.com/v1/albums/7nR0FDiIhGlZ0vJGWT0xib", "id": "7nR0FDiIhGlZ0vJGWT0xib", "images": [{"height": 640, "url": "https://i.scdn.co/image/ab67616d0000b273b977b7646e5d382650b2fcf8", "width": 640}, {"height": 300, "url": "https://i.scdn.co/image/ab67616d00001e02b977b7646e5d382650b2fcf8", "width": 300}, {"height": 64, "url": "https://i.scdn.co/image/ab67616d00004851b977b7646e5d382650b2fcf8", "width": 64}], "name": "Do Ya Think I'm Sexy - Big On the Internet", "release_date": "2022-03-04", "release_date_precision": "day", "total_tracks": 40, "type": "album", "uri": "spotify:album:7nR0FDiIhGlZ0vJGWT0xib"}, "artists": [{"external_urls": {"spotify": "https://open.spotify.com/artist/6TLwD7HPWuiOzvXEa3oCNe"}, "href": "https://api.spotify.com/v1/artists/6TLwD7HPWuiOzvXEa3oCNe", "id": "6TLwD7HPWuiOzvXEa3oCNe", "name": "Oliver Tree", "type": "artist", "uri": "spotify:artist:6TLwD7HPWuiOzvXEa3oCNe"}], "disc_number": 1, "duration_ms": 161803, "explicit": false, "external_ids": {"isrc": "USAT22007153"}, "external_urls": {"spotify": "https://open.spotify.com/track/5WAyHA98Zl1yAZO0v2pnjC"}, "href": "https://api.spotify.com/v1/tracks/5WAyHA98Zl1yAZO0v2pnjC", "id": "5WAyHA98Zl1yAZO0v2pnjC", "is_local": false, "is_playable": true, "name": "Life Goes On", "popularity": 0, "preview_url": "https://p.scdn.co/mp3-preview/8263e9905c7744096b876feb779190c14eee550c?cid=41d11c64c99f4295b22b262d02a041ff", "track_number": 10, "type": "track", "uri": "spotify:track:5WAyHA98Zl1yAZO0v2pnjC"}, {"album": {"album_type": "album", "artists": [{"external_urls": {"spotify": "https://open.spotify.com/artist/0LyfQWJT6nXafLPZqxe9Of"}, "href": "https://api.spotify.com/v1/artists/0LyfQWJT6nXafLPZqxe9Of", "id": "0LyfQWJT6nXafLPZqxe9Of", "name": "Various Artists", "type": "artist", "uri": "spotify:artist:0LyfQWJT6nXafLPZqxe9Of"}], "external_urls": {"spotify": "https://open.spotify.com/album/0PJMFssXtGXQi8VPji5NgW"}, "href": "https://api.spotify.com/v1/albums/0PJMFssXtGXQi8VPji5NgW", "id": "0PJMFssXtGXQi8VPji5NgW", "images": [{"height": 640, "url": "https://i.scdn.co/image/ab67616d0000b27309f9c73229f7b31f63f846c8", "width": 640}, {"height": 300, "url": "https://i.scdn.co/image/ab67616d00001e0209f9c73229f7b31f63f846c8", "width": 300}, {"height": 64, "url": "https://i.scdn.co/image/ab67616d0000485109f9c73229f7b31f63f846c8", "width": 64}], "name": "I Look Real Good Today - Certified Hits", "release_date": "2022-02-25", "release_date_precision": "day", "total_tracks": 45, "type": "album", "uri": "spotify:album:0PJMFssXtGXQi8VPji5NgW"}, "artists": [{"external_urls": {"spotify": "https://open.spotify.com/artist/6TLwD7HPWuiOzvXEa3oCNe"}, "href": "https://api.spotify.com/v1/artists/6TLwD7HPWuiOzvXEa3oCNe", "id": "6TLwD7HPWuiOzvXEa3oCNe", "name": "Oliver Tree", "type": "artist", "uri": "spotify:artist:6TLwD7HPWuiOzvXEa3oCNe"}], "disc_number": 1, "duration_ms": 161803, "explicit": false, "external_ids": {"isrc": "USAT22007153"}, "external_urls": {"spotify": "https://open.spotify.com/track/3ORXWjNPnXhUateHoz5aCR"}, "href": "https://api.spotify.com/v1/tracks/3ORXWjNPnXhUateHoz5aCR", "id": "3ORXWjNPnXhUateHoz5aCR", "is_local": false, "is_playable": true, "name": "Life Goes On", "popularity": 0, "preview_url": "https://p.scdn.co/mp3-preview/8263e9905c7744096b876feb779190c14eee550c?cid=41d11c64c99f4295b22b262d02a041ff", "track_number": 12, "type": "track", "uri": "spotify:track:3ORXWjNPnXhUateHoz5aCR"}, {"album": {"album_type": "album", "artists": [{"external_urls": {"spotify": "https://open.spotify.com/artist/0LyfQWJT6nXafLPZqxe9Of"}, "href": "https://api.spotify.com/v1/artists/0LyfQWJT6nXafLPZqxe9Of", "id": "0LyfQWJT6nXafLPZqxe9Of", "name": "Various Artists", "type": "artist", "uri": "spotify:artist:0LyfQWJT6nXafLPZqxe9Of"}], "external_urls": {"spotify": "https://open.spotify.com/album/67eRBP1zGP3JLv3IC79lNl"}, "href": "https://api.spotify.com/v1/albums/67eRBP1zGP3JLv3IC79lNl", "id": "67eRBP1zGP3JLv3IC79lNl", "images": [{"height": 640, "url": "https://i.scdn.co/image/ab67616d0000b27369031a3ad05880d21280f04e", "width": 640}, {"height": 300, "url": "https://i.scdn.co/image/ab67616d00001e0269031a3ad05880d21280f04e", "width": 300}, {"height": 64, "url": "https://i.scdn.co/image/ab67616d0000485169031a3ad05880d21280f04e", "width": 64}], "name": "2010's-2020's Retrogamer", "release_date": "2022-02-25", "release_date_precision": "day", "total_tracks": 50, "type": "album", "uri": "spotify:album:67eRBP1zGP3JLv3IC79lNl"}, "artists": [{"external_urls": {"spotify": "https://open.spotify.com/artist/6TLwD7HPWuiOzvXEa3oCNe"}, "href": "https://api.spotify.com/v1/artists/6TLwD7HPWuiOzvXEa3oCNe", "id": "6TLwD7HPWuiOzvXEa3oCNe", "name": "Oliver Tree", "type": "artist", "uri": "spotify:artist:6TLwD7HPWuiOzvXEa3oCNe"}], "disc_number": 1, "duration_ms": 161803, "explicit": false, "external_ids": {"isrc": "USAT22007153"}, "external_urls": {"spotify": "https://open.spotify.com/track/7tYOPj795q9aD61sNZeAoq"}, "href": "https://api.spotify.com/v1/tracks/7tYOPj795q9aD61sNZeAoq", "id": "7tYOPj795q9aD61sNZeAoq", "is_local": false, "is_playable": true, "name": "Life Goes On", "popularity": 0, "preview_url": "https://p.scdn.co/mp3-preview/8263e9905c7744096b876feb779190c14eee550c?cid=41d11c64c99f4295b22b262d02a041ff", "track_number": 8, "type": "track", "uri": "spotify:track:7tYOPj795q9aD61sNZeAoq"}, {"album": {"album_type": "compilation", "artists": [{"external_urls": {"spotify": "https://open.spotify.com/artist/0LyfQWJT6nXafLPZqxe9Of"}, "href": "https://api.spotify.com/v1/artists/0LyfQWJT6nXafLPZqxe9Of", "id": "0LyfQWJT6nXafLPZqxe9Of", "name": "Various Artists", "type": "artist", "uri": "spotify:artist:0LyfQWJT6nXafLPZqxe9Of"}], "external_urls": {"spotify": "https://open.spotify.com/album/406GPCEMnbCaK3i59haQD4"}, "href": "https://api.spotify.com/v1/albums/406GPCEMnbCaK3i59haQD4", "id": "406GPCEMnbCaK3i59haQD4", "images": [{"height": 640, "url": "https://i.scdn.co/image/ab67616d0000b27375b5cc63b67900735505ca34", "width": 640}, {"height": 300, "url": "https://i.scdn.co/image/ab67616d00001e0275b5cc63b67900735505ca34", "width": 300}, {"height": 64, "url": "https://i.scdn.co/image/ab67616d0000485175b5cc63b67900735505ca34", "width": 64}], "name": "Soft Car Songs", "release_date": "2022-03-04", "release_date_precision": "day", "total_tracks": 35, "type": "album", "uri": "spotify:album:406GPCEMnbCaK3i59haQD4"}, "artists": [{"external_urls": {"spotify": "https://open.spotify.com/artist/6TLwD7HPWuiOzvXEa3oCNe"}, "href": "https://api.spotify.com/v1/artists/6TLwD7HPWuiOzvXEa3oCNe", "id": "6TLwD7HPWuiOzvXEa3oCNe", "name": "Oliver Tree", "type": "artist", "uri": "spotify:artist:6TLwD7HPWuiOzvXEa3oCNe"}], "disc_number": 1, "duration_ms": 161803, "explicit": false, "external_ids": {"isrc": "USAT22007153"}, "external_urls": {"spotify": "https://open.spotify.com/track/1i8pUMWDrISe1pAKYBSu4q"}, "href": "https://api.spotify.com/v1/tracks/1i8pUMWDrISe1pAKYBSu4q", "id": "1i8pUMWDrISe1pAKYBSu4q", "is_local": false, "is_playable": true, "name": "Life Goes On", "popularity": 0, "preview_url": "https://p.scdn.co/mp3-preview/8263e9905c7744096b876feb779190c14eee550c?cid=41d11c64c99f4295b22b262d02a041ff", "track_number": 3, "type": "track", "uri": "spotify:track:1i8pUMWDrISe1pAKYBSu4q"}, {"album": {"album_type": "album", "artists": [{"external_urls": {"spotify": "https://open.spotify.com/artist/0LyfQWJT6nXafLPZqxe9Of"}, "href": "https://api.spotify.com/v1/artists/0LyfQWJT6nXafLPZqxe9Of", "id": "0LyfQWJT6nXafLPZqxe9Of", "name": "Various Artists", "type": "artist", "uri": "spotify:artist:0LyfQWJT6nXafLPZqxe9Of"}], "external_urls": {"spotify": "https://open.spotify.com/album/6j363LLKT8oeRxCOx5FrER"}, "href": "https://api.spotify.com/v1/albums/6j363LLKT8oeRxCOx5FrER", "id": "6j363LLKT8oeRxCOx5FrER", "images": [{"height": 640, "url": "https://i.scdn.co/image/ab67616d0000b273f697b7e2baa4cbef22cc1e39", "width": 640}, {"height": 300, "url": "https://i.scdn.co/image/ab67616d00001e02f697b7e2baa4cbef22cc1e39", "width": 300}, {"height": 64, "url": "https://i.scdn.co/image/ab67616d00004851f697b7e2baa4cbef22cc1e39", "width": 64}], "name": "Pity Party - Trending Hits", "release_date": "2022-03-04", "release_date_precision": "day", "total_tracks": 50, "type": "album", "uri": "spotify:album:6j363LLKT8oeRxCOx5FrER"}, "artists": [{"external_urls": {"spotify": "https://open.spotify.com/artist/6TLwD7HPWuiOzvXEa3oCNe"}, "href": "https://api.spotify.com/v1/artists/6TLwD7HPWuiOzvXEa3oCNe", "id": "6TLwD7HPWuiOzvXEa3oCNe", "name": "Oliver Tree", "type": "artist", "uri": "spotify:artist:6TLwD7HPWuiOzvXEa3oCNe"}], "disc_number": 1, "duration_ms": 189969, "explicit": false, "external_ids": {"isrc": "USAT22107445"}, "external_urls": {"spotify": "https://open.spotify.com/track/1n66J8nlj8Ix0GafXiyQ05"}, "href": "https://api.spotify.com/v1/tracks/1n66J8nlj8Ix0GafXiyQ05", "id": "1n66J8nlj8Ix0GafXiyQ05", "is_local": false, "is_playable": true, "name": "Cowboys Don\u2019t Cry", "popularity": 0, "preview_url": "https://p.scdn.co/mp3-preview/17f52c1fa9882fe9737a69b41830c1754fedc1e3?cid=41d11c64c99f4295b22b262d02a041ff", "track_number": 19, "type": "track", "uri": "spotify:track:1n66J8nlj8Ix0GafXiyQ05"}]